[
  {
    "id": "43011",
    "rank": "86",
    "workers": "1368",
    "company": "Nutanix",
    "url": "nutanix",
    "state_l": "California",
    "state_s": "CA",
    "city": "San Jose",
    "growth": "3565.8366",
    "revenue": "241432000",
    "ifmid": "20",
    "ifiid": "9",
    "metro": "San Jose",
    "industry": "Software",
    "yrs_on_list": "1"
  },
  {
    "id": "43084",
    "rank": "180",
    "workers": "1000",
    "company": "A.M. Staffing Group",
    "url": "am-staffing-group",
    "state_l": "Illinois",
    "state_s": "IL",
    "city": "Elgin",
    "growth": "2055.1395",
    "revenue": "2554530",
    "ifmid": "17",
    "ifiid": "21",
    "metro": "Chicago",
    "industry": "Human Resources",
    "yrs_on_list": "1"
  },
  {
    "id": "26343",
    "rank": "275",
    "workers": "7756",
    "company": "Bowlmor AMF",
    "url": "bowlmor-amf",
    "state_l": "New York",
    "state_s": "NY",
    "city": "New York",
    "growth": "1422.0219",
    "revenue": "565731000",
    "ifmid": "9",
    "ifiid": "11",
    "metro": "New York City",
    "industry": "Food & Beverage",
    "yrs_on_list": "3"
  },
  {
    "id": "23038",
    "rank": "288",
    "workers": "4900",
    "company": "TaskUs",
    "url": "taskus",
    "state_l": "California",
    "state_s": "CA",
    "city": "Santa Monica",
    "growth": "1354.8586",
    "revenue": "53653278",
    "ifmid": "2",
    "ifiid": "17",
    "metro": "Los Angeles",
    "industry": "Business Products & Services",
    "yrs_on_list": "4"
  },
  {
    "id": "36881",
    "rank": "334",
    "workers": "698",
    "company": "NEKTER JUICE BAR",
    "url": "nekter-juice-bar",
    "state_l": "California",
    "state_s": "CA",
    "city": "Santa Ana",
    "growth": "1146.3131",
    "revenue": "36705092",
    "ifmid": "2",
    "ifiid": "11",
    "metro": "Los Angeles",
    "industry": "Food & Beverage",
    "yrs_on_list": "2"
  },
  {
    "id": "25564",
    "rank": "373",
    "workers": "2140",
    "company": "MOD Pizza",
    "url": "mod-pizza",
    "state_l": "Washington",
    "state_s": "WA",
    "city": "Bellevue",
    "growth": "1028.7516",
    "revenue": "65158698",
    "ifmid": "23",
    "ifiid": "11",
    "metro": "Seattle",
    "industry": "Food & Beverage",
    "yrs_on_list": "3"
  },
  {
    "id": "38072",
    "rank": "386",
    "workers": "675",
    "company": "ArroHealth",
    "url": "arrohealth",
    "state_l": "New York",
    "state_s": "NY",
    "city": "Hauppauge",
    "growth": "990.0337",
    "revenue": "42108000",
    "ifmid": "9",
    "ifiid": "10",
    "metro": "New York City",
    "industry": "Health",
    "yrs_on_list": "2"
  },
  {
    "id": "26431",
    "rank": "481",
    "workers": "900",
    "company": "Jeunesse Global",
    "url": "jeunesse-global",
    "state_l": "Florida",
    "state_s": "FL",
    "city": "Lake Mary",
    "growth": "791.0651",
    "revenue": "1019683612",
    "ifmid": "68",
    "ifiid": "4",
    "metro": "Orlando, FL",
    "industry": "Consumer Products & Services",
    "yrs_on_list": "3"
  },
  {
    "id": "1553",
    "rank": "500",
    "workers": "934",
    "company": "Vixxo",
    "url": "vixxo",
    "state_l": "Arizona",
    "state_s": "AZ",
    "city": "Scottsdale",
    "growth": "757.6213",
    "revenue": "693622000",
    "ifmid": "46",
    "ifiid": "17",
    "metro": "Phoenix",
    "industry": "Business Products & Services",
    "yrs_on_list": "8"
  },
  {
    "id": "43290",
    "rank": "501",
    "workers": "750",
    "company": "Akorbi",
    "url": "akorbi",
    "state_l": "Texas",
    "state_s": "TX",
    "city": "Plano",
    "growth": "757.5059",
    "revenue": "23368365",
    "ifmid": "8",
    "ifiid": "17",
    "metro": "Dallas",
    "industry": "Business Products & Services",
    "yrs_on_list": "1"
  },
  {
    "id": "25492",
    "rank": "535",
    "workers": "1118",
    "company": "Sovereign Health Group",
    "url": "sovereign-health-group",
    "state_l": "California",
    "state_s": "CA",
    "city": "San Clemente",
    "growth": "721.4955",
    "revenue": "74683601",
    "ifmid": "2",
    "ifiid": "10",
    "metro": "Los Angeles",
    "industry": "Health",
    "yrs_on_list": "3"
  },
  {
    "id": "43323",
    "rank": "580",
    "workers": "1500",
    "company": "Incedo",
    "url": "incedo",
    "state_l": "California",
    "state_s": "CA",
    "city": "Santa Clara",
    "growth": "671.3633",
    "revenue": "27580088",
    "ifmid": "20",
    "ifiid": "8",
    "metro": "San Jose",
    "industry": "IT Services",
    "yrs_on_list": "1"
  },
  {
    "id": "43366",
    "rank": "671",
    "workers": "3500",
    "company": "NEO Tech",
    "url": "neo-tech",
    "state_l": "California",
    "state_s": "CA",
    "city": "Chatsworth",
    "growth": "582.9763",
    "revenue": "603471000",
    "ifmid": "2",
    "ifiid": "15",
    "metro": "Los Angeles",
    "industry": "Manufacturing",
    "yrs_on_list": "1"
  },
  {
    "id": "43371",
    "rank": "679",
    "workers": "2290",
    "company": "TechStyle Fashion Group",
    "url": "techstyle-fashion-group",
    "state_l": "California",
    "state_s": "CA",
    "city": "El Segundo",
    "growth": "578.7398",
    "revenue": "505199611",
    "ifmid": "2",
    "ifiid": "18",
    "metro": "Los Angeles",
    "industry": "Retail",
    "yrs_on_list": "1"
  },
  {
    "id": "24677",
    "rank": "687",
    "workers": "2597",
    "company": "Loyal Source Government Services",
    "url": "loyal-source-government-services",
    "state_l": "Florida",
    "state_s": "FL",
    "city": "Orlando",
    "growth": "572.553",
    "revenue": "146960924",
    "ifmid": "68",
    "ifiid": "7",
    "metro": "Orlando, FL",
    "industry": "Government Services",
    "yrs_on_list": "3"
  },
  {
    "id": "42870",
    "rank": "763",
    "workers": "1282",
    "company": "Square",
    "url": "square",
    "state_l": "California",
    "state_s": "CA",
    "city": "San Francisco",
    "growth": "522.8185",
    "revenue": "1267118000",
    "ifmid": "4",
    "ifiid": "2",
    "metro": "San Francisco",
    "industry": "Financial Services",
    "yrs_on_list": "1"
  },
  {
    "id": "2437",
    "rank": "832",
    "workers": "4693",
    "company": "Account Control Technology",
    "url": "account-control-technology",
    "state_l": "California",
    "state_s": "CA",
    "city": "Woodland Hills",
    "growth": "477.2659",
    "revenue": "258972667",
    "ifmid": "2",
    "ifiid": "2",
    "metro": "Los Angeles",
    "industry": "Financial Services",
    "yrs_on_list": "10"
  },
  {
    "id": "36964",
    "rank": "847",
    "workers": "3000",
    "company": "Daseke",
    "url": "daseke",
    "state_l": "Texas",
    "state_s": "TX",
    "city": "Addison",
    "growth": "467.9752",
    "revenue": "678844848",
    "ifmid": "8",
    "ifiid": "6",
    "metro": "Dallas",
    "industry": "Logistics & Transportation",
    "yrs_on_list": "2"
  },
  {
    "id": "21325",
    "rank": "876",
    "workers": "3400",
    "company": "Appleton",
    "url": "appleton",
    "state_l": "Alabama",
    "state_s": "AL",
    "city": "Huntsville",
    "growth": "453.1698",
    "revenue": "22869709",
    "ifmid": "69",
    "ifiid": "19",
    "metro": "Huntsville, AL",
    "industry": "Education",
    "yrs_on_list": "5"
  },
  {
    "id": "24946",
    "rank": "877",
    "workers": "1022",
    "company": "Connexion Point",
    "url": "connexion-point",
    "state_l": "Utah",
    "state_s": "UT",
    "city": "Salt Lake City",
    "growth": "452.6565",
    "revenue": "40058651",
    "ifmid": "12",
    "ifiid": "10",
    "metro": "Salt Lake City",
    "industry": "Health",
    "yrs_on_list": "3"
  },
  {
    "id": "26544",
    "rank": "907",
    "workers": "840",
    "company": "Material Handling Services",
    "url": "material-handling-services",
    "state_l": "Ohio",
    "state_s": "OH",
    "city": "Perrysburg",
    "growth": "440.6015",
    "revenue": "301396130",
    "ifmid": "300",
    "ifiid": "17",
    "metro": "Toledo, OH",
    "industry": "Business Products & Services",
    "yrs_on_list": "3"
  },
  {
    "id": "26210",
    "rank": "927",
    "workers": "600",
    "company": "Response Team 1",
    "url": "response-team-1",
    "state_l": "Illinois",
    "state_s": "IL",
    "city": "Chicago",
    "growth": "429.6205",
    "revenue": "166993370",
    "ifmid": "17",
    "ifiid": "20",
    "metro": "Chicago",
    "industry": "Construction",
    "yrs_on_list": "3"
  },
  {
    "id": "37239",
    "rank": "992",
    "workers": "600",
    "company": "Safe Haven Security Services",
    "url": "safe-haven-security-services",
    "state_l": "Missouri",
    "state_s": "MO",
    "city": "Kansas City",
    "growth": "403.9129",
    "revenue": "53150548",
    "ifmid": "21",
    "ifiid": "13",
    "metro": "Kansas City, MO-KS",
    "industry": "Security",
    "yrs_on_list": "2"
  },
  {
    "id": "43512",
    "rank": "1001",
    "workers": "600",
    "company": "Palmetto Partners",
    "url": "palmetto-partners",
    "state_l": "Virginia",
    "state_s": "VA",
    "city": "Alexandria",
    "growth": "396.5799",
    "revenue": "4019596",
    "ifmid": "3",
    "ifiid": "7",
    "metro": "Washington, DC",
    "industry": "Government Services",
    "yrs_on_list": "1"
  },
  {
    "id": "24519",
    "rank": "1010",
    "workers": "1464",
    "company": "American Family Care",
    "url": "american-family-care",
    "state_l": "Alabama",
    "state_s": "AL",
    "city": "Birmingham",
    "growth": "392.5898",
    "revenue": "433176695",
    "ifmid": "140",
    "ifiid": "10",
    "metro": "Birmingham-Hoover, AL",
    "industry": "Health",
    "yrs_on_list": "3"
  },
  {
    "id": "727",
    "rank": "1018",
    "workers": "1936",
    "company": "Pinnacle Group",
    "url": "pinnacle-group",
    "state_l": "Texas",
    "state_s": "TX",
    "city": "Dallas",
    "growth": "388.9403",
    "revenue": "1161466598",
    "ifmid": "8",
    "ifiid": "8",
    "metro": "Dallas",
    "industry": "IT Services",
    "yrs_on_list": "11"
  },
  {
    "id": "25855",
    "rank": "1028",
    "workers": "817",
    "company": "hCentive",
    "url": "hcentive",
    "state_l": "Virginia",
    "state_s": "VA",
    "city": "Reston",
    "growth": "384.4425",
    "revenue": "50538267",
    "ifmid": "3",
    "ifiid": "10",
    "metro": "Washington, DC",
    "industry": "Health",
    "yrs_on_list": "3"
  },
  {
    "id": "43533",
    "rank": "1039",
    "workers": "850",
    "company": "Elite Medical Scribes",
    "url": "elite-medical-scribes",
    "state_l": "Minnesota",
    "state_s": "MN",
    "city": "Bloomington",
    "growth": "379.8344",
    "revenue": "12986104",
    "ifmid": "13",
    "ifiid": "10",
    "metro": "Minneapolis",
    "industry": "Health",
    "yrs_on_list": "1"
  },
  {
    "id": "37588",
    "rank": "1063",
    "workers": "785",
    "company": "HighJump",
    "url": "highjump",
    "state_l": "Minnesota",
    "state_s": "MN",
    "city": "Minneapolis",
    "growth": "368.6169",
    "revenue": "164497212",
    "ifmid": "13",
    "ifiid": "9",
    "metro": "Minneapolis",
    "industry": "Software",
    "yrs_on_list": "2"
  },
  {
    "id": "21173",
    "rank": "1123",
    "workers": "730",
    "company": "MediaMath",
    "url": "mediamath",
    "state_l": "New York",
    "state_s": "NY",
    "city": "New York",
    "growth": "344.3958",
    "revenue": "601000000",
    "ifmid": "9",
    "ifiid": "5",
    "metro": "New York City",
    "industry": "Advertising & Marketing",
    "yrs_on_list": "4"
  },
  {
    "id": "21071",
    "rank": "1127",
    "workers": "3006",
    "company": "Movement Mortgage",
    "url": "movement-mortgage",
    "state_l": "South Carolina",
    "state_s": "SC",
    "city": "Fort Mill",
    "growth": "342.7163",
    "revenue": "363202153",
    "ifmid": "43",
    "ifiid": "2",
    "metro": "Charlotte",
    "industry": "Financial Services",
    "yrs_on_list": "4"
  },
  {
    "id": "19472",
    "rank": "1148",
    "workers": "9255",
    "company": "ScribeAmerica",
    "url": "scribeamerica",
    "state_l": "Florida",
    "state_s": "FL",
    "city": "Fort Lauderdale",
    "growth": "338.0706",
    "revenue": "141349684",
    "ifmid": "1",
    "ifiid": "10",
    "metro": "Miami",
    "industry": "Health",
    "yrs_on_list": "6"
  },
  {
    "id": "25647",
    "rank": "1168",
    "workers": "2942",
    "company": "EXOS",
    "url": "exos",
    "state_l": "Arizona",
    "state_s": "AZ",
    "city": "Phoenix",
    "growth": "332.4397",
    "revenue": "129488645",
    "ifmid": "46",
    "ifiid": "10",
    "metro": "Phoenix",
    "industry": "Health",
    "yrs_on_list": "3"
  },
  {
    "id": "43590",
    "rank": "1205",
    "workers": "1777",
    "company": "GrapeTree Medical Staffing",
    "url": "grapetree-medical-staffing",
    "state_l": "Iowa",
    "state_s": "IA",
    "city": "Milford",
    "growth": "324.729",
    "revenue": "20025037",
    "ifmid": "331",
    "ifiid": "10",
    "metro": "Spirit Lake, IA",
    "industry": "Health",
    "yrs_on_list": "1"
  },
  {
    "id": "22910",
    "rank": "1213",
    "workers": "750",
    "company": "OneSource Virtual",
    "url": "onesource-virtual",
    "state_l": "Texas",
    "state_s": "TX",
    "city": "Irving",
    "growth": "320.9836",
    "revenue": "95922022",
    "ifmid": "8",
    "ifiid": "17",
    "metro": "Dallas",
    "industry": "Business Products & Services",
    "yrs_on_list": "4"
  },
  {
    "id": "37594",
    "rank": "1216",
    "workers": "730",
    "company": "Fusion Medical Staffing",
    "url": "fusion-medical-staffing",
    "state_l": "Nebraska",
    "state_s": "NE",
    "city": "Omaha",
    "growth": "319.3763",
    "revenue": "65008532",
    "ifmid": "97",
    "ifiid": "10",
    "metro": "Omaha-Council Bluffs, NE-IA",
    "industry": "Health",
    "yrs_on_list": "2"
  },
  {
    "id": "37106",
    "rank": "1260",
    "workers": "5000",
    "company": "loanDepot",
    "url": "loandepot",
    "state_l": "California",
    "state_s": "CA",
    "city": "Foothill Ranch",
    "growth": "307.1024",
    "revenue": "922359827",
    "ifmid": "2",
    "ifiid": "2",
    "metro": "Los Angeles",
    "industry": "Financial Services",
    "yrs_on_list": "2"
  },
  {
    "id": "23184",
    "rank": "1317",
    "workers": "788",
    "company": "Mid Atlantic Professionals",
    "url": "mid-atlantic-professionals",
    "state_l": "Maryland",
    "state_s": "MD",
    "city": "Germantown",
    "growth": "294.2748",
    "revenue": "38514631",
    "ifmid": "3",
    "ifiid": "7",
    "metro": "Washington, DC",
    "industry": "Government Services",
    "yrs_on_list": "4"
  },
  {
    "id": "25781",
    "rank": "1330",
    "workers": "731",
    "company": "AMPAL Group",
    "url": "ampal-group",
    "state_l": "New Jersey",
    "state_s": "NJ",
    "city": "Green Brook",
    "growth": "290.3709",
    "revenue": "34637913",
    "ifmid": "9",
    "ifiid": "11",
    "metro": "New York City",
    "industry": "Food & Beverage",
    "yrs_on_list": "2"
  },
  {
    "id": "21357",
    "rank": "1367",
    "workers": "4000",
    "company": "CCS Construction Staffing",
    "url": "ccs-construction-staffing",
    "state_l": "North Carolina",
    "state_s": "NC",
    "city": "Charlotte",
    "growth": "280.6941",
    "revenue": "28135588",
    "ifmid": "43",
    "ifiid": "21",
    "metro": "Charlotte",
    "industry": "Human Resources",
    "yrs_on_list": "5"
  },
  {
    "id": "43652",
    "rank": "1371",
    "workers": "845",
    "company": "Schlotzsky's and Dairy Queen",
    "url": "schlotzskys-and-dairy-queen",
    "state_l": "Texas",
    "state_s": "TX",
    "city": "Irving",
    "growth": "280.2669",
    "revenue": "20963075",
    "ifmid": "8",
    "ifiid": "11",
    "metro": "Dallas",
    "industry": "Food & Beverage",
    "yrs_on_list": "1"
  },
  {
    "id": "21198",
    "rank": "1407",
    "workers": "795",
    "company": "WeddingWire",
    "url": "weddingwire",
    "state_l": "Maryland",
    "state_s": "MD",
    "city": "Chevy Chase",
    "growth": "271.5199",
    "revenue": "72949089",
    "ifmid": "3",
    "ifiid": "4",
    "metro": "Washington, DC",
    "industry": "Consumer Products & Services",
    "yrs_on_list": "5"
  },
  {
    "id": "43671",
    "rank": "1448",
    "workers": "791",
    "company": "The Revenue Optimization Companies",
    "url": "the-revenue-optimization-companies",
    "state_l": "Florida",
    "state_s": "FL",
    "city": "Coral Gables",
    "growth": "264.2484",
    "revenue": "30550508",
    "ifmid": "1",
    "ifiid": "18",
    "metro": "Miami",
    "industry": "Retail",
    "yrs_on_list": "1"
  },
  {
    "id": "25677",
    "rank": "1459",
    "workers": "613",
    "company": "Nordic",
    "url": "nordic",
    "state_l": "Wisconsin",
    "state_s": "WI",
    "city": "Madison",
    "growth": "262.6873",
    "revenue": "137154267",
    "ifmid": "78",
    "ifiid": "10",
    "metro": "Madison, WI",
    "industry": "Health",
    "yrs_on_list": "3"
  },
  {
    "id": "37182",
    "rank": "1465",
    "workers": "1762",
    "company": "Workbox Staffing",
    "url": "workbox-staffing",
    "state_l": "Michigan",
    "state_s": "MI",
    "city": "Grand Rapids",
    "growth": "261.8919",
    "revenue": "43785296",
    "ifmid": "219",
    "ifiid": "21",
    "metro": "Grand Rapids-Wyoming, MI",
    "industry": "Human Resources",
    "yrs_on_list": "2"
  },
  {
    "id": "21082",
    "rank": "1469",
    "workers": "1640",
    "company": "Four Foods Group",
    "url": "four-foods-group",
    "state_l": "Utah",
    "state_s": "UT",
    "city": "American Fork",
    "growth": "261.4537",
    "revenue": "79482871",
    "ifmid": "48",
    "ifiid": "11",
    "metro": "Provo-Orem, UT",
    "industry": "Food & Beverage",
    "yrs_on_list": "5"
  },
  {
    "id": "25528",
    "rank": "1490",
    "workers": "839",
    "company": "Home Base Appraisal Management",
    "url": "home-base-appraisal-management",
    "state_l": "Utah",
    "state_s": "UT",
    "city": "Sandy",
    "growth": "256.2746",
    "revenue": "8692950",
    "ifmid": "12",
    "ifiid": "3",
    "metro": "Salt Lake City",
    "industry": "Real Estate",
    "yrs_on_list": "2"
  },
  {
    "id": "2118",
    "rank": "1513",
    "workers": "1138",
    "company": "Birch Communications",
    "url": "birch-communications",
    "state_l": "Georgia",
    "state_s": "GA",
    "city": "Atlanta",
    "growth": "250.5956",
    "revenue": "591222327",
    "ifmid": "29",
    "ifiid": "14",
    "metro": "Atlanta",
    "industry": "Telecommunications",
    "yrs_on_list": "7"
  },
  {
    "id": "894",
    "rank": "1525",
    "workers": "1100",
    "company": "NT Concepts",
    "url": "nt-concepts",
    "state_l": "Virginia",
    "state_s": "VA",
    "city": "Vienna",
    "growth": "248.8559",
    "revenue": "85363506",
    "ifmid": "3",
    "ifiid": "8",
    "metro": "Washington, DC",
    "industry": "IT Services",
    "yrs_on_list": "8"
  },
  {
    "id": "21694",
    "rank": "1555",
    "workers": "1390",
    "company": "American Eagle Protective Services",
    "url": "american-eagle-protective-services",
    "state_l": "Texas",
    "state_s": "TX",
    "city": "Austin",
    "growth": "244.5775",
    "revenue": "99593611",
    "ifmid": "18",
    "ifiid": "13",
    "metro": "Austin",
    "industry": "Security",
    "yrs_on_list": "5"
  },
  {
    "id": "21997",
    "rank": "1598",
    "workers": "2504",
    "company": "ABC Phones of North Carolina",
    "url": "abc-phones-of-north-carolina",
    "state_l": "North Carolina",
    "state_s": "NC",
    "city": "Greenville",
    "growth": "236.2552",
    "revenue": "781903981",
    "ifmid": "277",
    "ifiid": "14",
    "metro": "Greenville, NC",
    "industry": "Telecommunications",
    "yrs_on_list": "6"
  },
  {
    "id": "23066",
    "rank": "1600",
    "workers": "1280",
    "company": "SearchPros Solutions",
    "url": "searchpros-solutions",
    "state_l": "California",
    "state_s": "CA",
    "city": "Citrus Heights",
    "growth": "236.0275",
    "revenue": "31904000",
    "ifmid": "1011",
    "ifiid": "21",
    "metro": "Sacramento, CA",
    "industry": "Human Resources",
    "yrs_on_list": "2"
  },
  {
    "id": "43727",
    "rank": "1630",
    "workers": "850",
    "company": "NoHo Hospitality Group",
    "url": "noho-hospitality-group",
    "state_l": "New York",
    "state_s": "NY",
    "city": "New York",
    "growth": "230.7141",
    "revenue": "66638882",
    "ifmid": "9",
    "ifiid": "11",
    "metro": "New York City",
    "industry": "Food & Beverage",
    "yrs_on_list": "1"
  },
  {
    "id": "37436",
    "rank": "1636",
    "workers": "688",
    "company": "Benchmark Realty",
    "url": "benchmark-realty",
    "state_l": "Tennessee",
    "state_s": "TN",
    "city": "Franklin",
    "growth": "229.4027",
    "revenue": "42709063",
    "ifmid": "82",
    "ifiid": "3",
    "metro": "Nashville",
    "industry": "Real Estate",
    "yrs_on_list": "2"
  },
  {
    "id": "1627",
    "rank": "1661",
    "workers": "1543",
    "company": "Access Information Management",
    "url": "access-information-management",
    "state_l": "California",
    "state_s": "CA",
    "city": "Livermore",
    "growth": "225.8225",
    "revenue": "193660110",
    "ifmid": "20",
    "ifiid": "17",
    "metro": "San Jose",
    "industry": "Business Products & Services",
    "yrs_on_list": "8"
  },
  {
    "id": "18532",
    "rank": "1758",
    "workers": "80000",
    "company": "Universal Services of America",
    "url": "universal-services-of-america",
    "state_l": "California",
    "state_s": "CA",
    "city": "Santa Ana",
    "growth": "212.1463",
    "revenue": "1641075000",
    "ifmid": "2",
    "ifiid": "13",
    "metro": "Los Angeles",
    "industry": "Security",
    "yrs_on_list": "7"
  },
  {
    "id": "1815",
    "rank": "1792",
    "workers": "850",
    "company": "US Tech Solutions",
    "url": "us-tech-solutions",
    "state_l": "New Jersey",
    "state_s": "NJ",
    "city": "Jersey City",
    "growth": "207.9118",
    "revenue": "115121730",
    "ifmid": "9",
    "ifiid": "8",
    "metro": "New York City",
    "industry": "IT Services",
    "yrs_on_list": "6"
  },
  {
    "id": "26329",
    "rank": "1835",
    "workers": "635",
    "company": "Alliance Health",
    "url": "alliance-health",
    "state_l": "Utah",
    "state_s": "UT",
    "city": "South Jordan",
    "growth": "202.8166",
    "revenue": "175408778",
    "ifmid": "12",
    "ifiid": "10",
    "metro": "Salt Lake City",
    "industry": "Health",
    "yrs_on_list": "3"
  },
  {
    "id": "26598",
    "rank": "1845",
    "workers": "1860",
    "company": "Point 2 Point Global Security",
    "url": "point-2-point-global-security",
    "state_l": "Texas",
    "state_s": "TX",
    "city": "Addison",
    "growth": "201.8434",
    "revenue": "39943153",
    "ifmid": "8",
    "ifiid": "13",
    "metro": "Dallas",
    "industry": "Security",
    "yrs_on_list": "3"
  },
  {
    "id": "22787",
    "rank": "1869",
    "workers": "884",
    "company": "Data Dimensions",
    "url": "data-dimensions",
    "state_l": "Wisconsin",
    "state_s": "WI",
    "city": "Janesville",
    "growth": "199.1537",
    "revenue": "72740158",
    "ifmid": "1042",
    "ifiid": "17",
    "metro": "Janesville-Beloit, WI",
    "industry": "Business Products & Services",
    "yrs_on_list": "4"
  },
  {
    "id": "154",
    "rank": "1871",
    "workers": "1040",
    "company": "College Hunks Hauling Junk and Moving",
    "url": "college-hunks-hauling-junk-and-moving",
    "state_l": "Florida",
    "state_s": "FL",
    "city": "Tampa",
    "growth": "198.8371",
    "revenue": "33709000",
    "ifmid": "7",
    "ifiid": "4",
    "metro": "Tampa",
    "industry": "Consumer Products & Services",
    "yrs_on_list": "7"
  },
  {
    "id": "43815",
    "rank": "1885",
    "workers": "1280",
    "company": "MedSpeed",
    "url": "medspeed",
    "state_l": "Illinois",
    "state_s": "IL",
    "city": "Elmhurst",
    "growth": "197.6931",
    "revenue": "59968274",
    "ifmid": "17",
    "ifiid": "10",
    "metro": "Chicago",
    "industry": "Health",
    "yrs_on_list": "1"
  },
  {
    "id": "5049",
    "rank": "1888",
    "workers": "1200",
    "company": "WorkForce Solutions Group",
    "url": "workforce-solutions-group",
    "state_l": "California",
    "state_s": "CA",
    "city": "Lake Forest",
    "growth": "197.6502",
    "revenue": "30340649",
    "ifmid": "2",
    "ifiid": "21",
    "metro": "Los Angeles",
    "industry": "Human Resources",
    "yrs_on_list": "3"
  },
  {
    "id": "20975",
    "rank": "1890",
    "workers": "720",
    "company": "Acquia",
    "url": "acquia",
    "state_l": "Massachusetts",
    "state_s": "MA",
    "city": "Boston",
    "growth": "197.4648",
    "revenue": "128011000",
    "ifmid": "6",
    "ifiid": "9",
    "metro": "Boston",
    "industry": "Software",
    "yrs_on_list": "5"
  },
  {
    "id": "24054",
    "rank": "1904",
    "workers": "3964",
    "company": "Freedom Mortgage",
    "url": "freedom-mortgage",
    "state_l": "New Jersey",
    "state_s": "NJ",
    "city": "Mount Laurel",
    "growth": "196.0264",
    "revenue": "762199793",
    "ifmid": "49",
    "ifiid": "2",
    "metro": "Philadelphia",
    "industry": "Financial Services",
    "yrs_on_list": "4"
  },
  {
    "id": "43834",
    "rank": "1954",
    "workers": "835",
    "company": "Dirty Robber",
    "url": "dirty-robber",
    "state_l": "California",
    "state_s": "CA",
    "city": "Los Angeles",
    "growth": "190.0796",
    "revenue": "3778942",
    "ifmid": "2",
    "ifiid": "12",
    "metro": "Los Angeles",
    "industry": "Media",
    "yrs_on_list": "1"
  },
  {
    "id": "43835",
    "rank": "1955",
    "workers": "617",
    "company": "PinnacleART",
    "url": "pinnacleart",
    "state_l": "Texas",
    "state_s": "TX",
    "city": "Pasadena",
    "growth": "190.0715",
    "revenue": "78265763",
    "ifmid": "22",
    "ifiid": "24",
    "metro": "Houston",
    "industry": "Engineering",
    "yrs_on_list": "1"
  },
  {
    "id": "23194",
    "rank": "1976",
    "workers": "800",
    "company": "North American Dental Group",
    "url": "north-american-dental-group",
    "state_l": "Pennsylvania",
    "state_s": "PA",
    "city": "New Castle",
    "growth": "188.2944",
    "revenue": "88044094",
    "ifmid": "220",
    "ifiid": "10",
    "metro": "New Castle, PA",
    "industry": "Health",
    "yrs_on_list": "4"
  },
  {
    "id": "37652",
    "rank": "2059",
    "workers": "1598",
    "company": "FCR",
    "url": "fcr",
    "state_l": "Oregon",
    "state_s": "OR",
    "city": "Eugene",
    "growth": "181.1253",
    "revenue": "48744642",
    "ifmid": "1016",
    "ifiid": "17",
    "metro": "Eugene, OR",
    "industry": "Business Products & Services",
    "yrs_on_list": "2"
  },
  {
    "id": "21636",
    "rank": "2061",
    "workers": "665",
    "company": "Advance Financial",
    "url": "advance-financial",
    "state_l": "Tennessee",
    "state_s": "TN",
    "city": "Nashville",
    "growth": "180.7002",
    "revenue": "101345137",
    "ifmid": "82",
    "ifiid": "2",
    "metro": "Nashville",
    "industry": "Financial Services",
    "yrs_on_list": "5"
  },
  {
    "id": "43873",
    "rank": "2079",
    "workers": "650",
    "company": "Sage IT",
    "url": "sage-it",
    "state_l": "Texas",
    "state_s": "TX",
    "city": "Frisco",
    "growth": "179.0764",
    "revenue": "35445299",
    "ifmid": "8",
    "ifiid": "8",
    "metro": "Dallas",
    "industry": "IT Services",
    "yrs_on_list": "1"
  },
  {
    "id": "23390",
    "rank": "2109",
    "workers": "800",
    "company": "Episource",
    "url": "episource",
    "state_l": "California",
    "state_s": "CA",
    "city": "Gardena",
    "growth": "175.9359",
    "revenue": "25940805",
    "ifmid": "2",
    "ifiid": "10",
    "metro": "Los Angeles",
    "industry": "Health",
    "yrs_on_list": "4"
  },
  {
    "id": "25109",
    "rank": "2139",
    "workers": "620",
    "company": "VIVA Pediatrics",
    "url": "viva-pediatrics",
    "state_l": "Texas",
    "state_s": "TX",
    "city": "Richardson",
    "growth": "173.5506",
    "revenue": "17987643",
    "ifmid": "8",
    "ifiid": "10",
    "metro": "Dallas",
    "industry": "Health",
    "yrs_on_list": "3"
  },
  {
    "id": "21768",
    "rank": "2144",
    "workers": "613",
    "company": "Alert Logic",
    "url": "alert-logic",
    "state_l": "Texas",
    "state_s": "TX",
    "city": "Houston",
    "growth": "172.4429",
    "revenue": "81079000",
    "ifmid": "22",
    "ifiid": "9",
    "metro": "Houston",
    "industry": "Software",
    "yrs_on_list": "5"
  },
  {
    "id": "19359",
    "rank": "2149",
    "workers": "649",
    "company": "Rimini Street",
    "url": "rimini-street",
    "state_l": "Nevada",
    "state_s": "NV",
    "city": "Las Vegas",
    "growth": "171.883",
    "revenue": "118818000",
    "ifmid": "1004",
    "ifiid": "8",
    "metro": "Las Vegas-Henderson-Paradise, NV",
    "industry": "IT Services",
    "yrs_on_list": "6"
  },
  {
    "id": "21761",
    "rank": "2165",
    "workers": "9100",
    "company": "Freddy's Frozen Custard & Steakburgers",
    "url": "freddys-frozen-custard-steakburgers",
    "state_l": "Kansas",
    "state_s": "KS",
    "city": "Wichita",
    "growth": "170.075",
    "revenue": "267077532",
    "ifmid": "104",
    "ifiid": "11",
    "metro": "Wichita, KS",
    "industry": "Food & Beverage",
    "yrs_on_list": "5"
  },
  {
    "id": "43909",
    "rank": "2186",
    "workers": "1262",
    "company": "Bay Equity Home Loans",
    "url": "bay-equity-home-loans",
    "state_l": "California",
    "state_s": "CA",
    "city": "Sausalito",
    "growth": "168.4235",
    "revenue": "97513040",
    "ifmid": "4",
    "ifiid": "2",
    "metro": "San Francisco",
    "industry": "Financial Services",
    "yrs_on_list": "1"
  },
  {
    "id": "24461",
    "rank": "2228",
    "workers": "1827",
    "company": "NorthStar Anesthesia",
    "url": "northstar-anesthesia",
    "state_l": "Texas",
    "state_s": "TX",
    "city": "Irving",
    "growth": "164.3167",
    "revenue": "343214872",
    "ifmid": "8",
    "ifiid": "10",
    "metro": "Dallas",
    "industry": "Health",
    "yrs_on_list": "3"
  },
  {
    "id": "1215",
    "rank": "2229",
    "workers": "1579",
    "company": "Universal Plant Services",
    "url": "universal-plant-services",
    "state_l": "Texas",
    "state_s": "TX",
    "city": "Deer Park",
    "growth": "164.2147",
    "revenue": "328637000",
    "ifmid": "22",
    "ifiid": "16",
    "metro": "Houston",
    "industry": "Energy",
    "yrs_on_list": "5"
  },
  {
    "id": "23515",
    "rank": "2236",
    "workers": "979",
    "company": "Eating Recovery Center",
    "url": "eating-recovery-center",
    "state_l": "Colorado",
    "state_s": "CO",
    "city": "Denver",
    "growth": "162.819",
    "revenue": "115410631",
    "ifmid": "30",
    "ifiid": "10",
    "metro": "Denver",
    "industry": "Health",
    "yrs_on_list": "4"
  },
  {
    "id": "19278",
    "rank": "2243",
    "workers": "7000",
    "company": "Smashburger",
    "url": "smashburger",
    "state_l": "Colorado",
    "state_s": "CO",
    "city": "Denver",
    "growth": "161.9996",
    "revenue": "194669116",
    "ifmid": "30",
    "ifiid": "11",
    "metro": "Denver",
    "industry": "Food & Beverage",
    "yrs_on_list": "6"
  },
  {
    "id": "1773",
    "rank": "2258",
    "workers": "1196",
    "company": "Conservice",
    "url": "conservice",
    "state_l": "Utah",
    "state_s": "UT",
    "city": "Logan",
    "growth": "160.728",
    "revenue": "107538188",
    "ifmid": "186",
    "ifiid": "16",
    "metro": "Logan, UT-ID",
    "industry": "Energy",
    "yrs_on_list": "9"
  },
  {
    "id": "21639",
    "rank": "2267",
    "workers": "1165",
    "company": "Chetu",
    "url": "chetu",
    "state_l": "Florida",
    "state_s": "FL",
    "city": "Plantation",
    "growth": "160.2291",
    "revenue": "31505576",
    "ifmid": "1",
    "ifiid": "9",
    "metro": "Miami",
    "industry": "Software",
    "yrs_on_list": "5"
  },
  {
    "id": "602",
    "rank": "2281",
    "workers": "3281",
    "company": "C2 Education",
    "url": "c2-education",
    "state_l": "Georgia",
    "state_s": "GA",
    "city": "Duluth",
    "growth": "159.0137",
    "revenue": "58394513",
    "ifmid": "29",
    "ifiid": "19",
    "metro": "Atlanta",
    "industry": "Education",
    "yrs_on_list": "5"
  },
  {
    "id": "21359",
    "rank": "2283",
    "workers": "1952",
    "company": "New American Funding",
    "url": "new-american-funding",
    "state_l": "California",
    "state_s": "CA",
    "city": "Tustin",
    "growth": "158.89",
    "revenue": "378640767",
    "ifmid": "2",
    "ifiid": "2",
    "metro": "Los Angeles",
    "industry": "Financial Services",
    "yrs_on_list": "4"
  },
  {
    "id": "20004",
    "rank": "2287",
    "workers": "1055",
    "company": "Russell Cellular",
    "url": "russell-cellular",
    "state_l": "Missouri",
    "state_s": "MO",
    "city": "Battlefield",
    "growth": "158.5293",
    "revenue": "225016763",
    "ifmid": "102",
    "ifiid": "18",
    "metro": "Springfield, MO",
    "industry": "Retail",
    "yrs_on_list": "6"
  },
  {
    "id": "17852",
    "rank": "2288",
    "workers": "691",
    "company": "EPIC Insurance Brokers and Consultants",
    "url": "epic-insurance-brokers-and-consultants",
    "state_l": "California",
    "state_s": "CA",
    "city": "San Francisco",
    "growth": "158.4609",
    "revenue": "173578579",
    "ifmid": "4",
    "ifiid": "1",
    "metro": "San Francisco",
    "industry": "Insurance",
    "yrs_on_list": "3"
  },
  {
    "id": "37654",
    "rank": "2291",
    "workers": "1498",
    "company": "Itransition",
    "url": "itransition",
    "state_l": "Texas",
    "state_s": "TX",
    "city": "Austin",
    "growth": "158.3144",
    "revenue": "18039094",
    "ifmid": "18",
    "ifiid": "9",
    "metro": "Austin",
    "industry": "Software",
    "yrs_on_list": "2"
  },
  {
    "id": "43937",
    "rank": "2296",
    "workers": "1230",
    "company": "Athene Holding",
    "url": "athene-holding",
    "state_l": "Iowa",
    "state_s": "IA",
    "city": "West Des Moines",
    "growth": "158.0138",
    "revenue": "2624000000",
    "ifmid": "161",
    "ifiid": "1",
    "metro": "Des Moines-West Des Moines, IA",
    "industry": "Insurance",
    "yrs_on_list": "1"
  },
  {
    "id": "3738",
    "rank": "2297",
    "workers": "620",
    "company": "Plasticard Locktech International",
    "url": "plasticard-locktech-international",
    "state_l": "North Carolina",
    "state_s": "NC",
    "city": "Asheville",
    "growth": "158.0048",
    "revenue": "93093719",
    "ifmid": "299",
    "ifiid": "15",
    "metro": "Asheville, NC",
    "industry": "Manufacturing",
    "yrs_on_list": "7"
  },
  {
    "id": "20333",
    "rank": "2310",
    "workers": "628",
    "company": "New Horizon Security Services",
    "url": "new-horizon-security-services",
    "state_l": "Virginia",
    "state_s": "VA",
    "city": "Manassas",
    "growth": "157.173",
    "revenue": "21770036",
    "ifmid": "3",
    "ifiid": "13",
    "metro": "Washington, DC",
    "industry": "Security",
    "yrs_on_list": "6"
  },
  {
    "id": "23561",
    "rank": "2324",
    "workers": "600",
    "company": "Ob Hospitalist Group",
    "url": "ob-hospitalist-group",
    "state_l": "South Carolina",
    "state_s": "SC",
    "city": "Mauldin",
    "growth": "155.9943",
    "revenue": "130730043",
    "ifmid": "1000",
    "ifiid": "10",
    "metro": "Greenville-Anderson-Mauldin, SC",
    "industry": "Health",
    "yrs_on_list": "4"
  },
  {
    "id": "26399",
    "rank": "2396",
    "workers": "5500",
    "company": "MS Companies",
    "url": "ms-companies",
    "state_l": "Indiana",
    "state_s": "IN",
    "city": "Indianapolis",
    "growth": "151.1152",
    "revenue": "87788759",
    "ifmid": "81",
    "ifiid": "17",
    "metro": "Indianapolis, IN",
    "industry": "Business Products & Services",
    "yrs_on_list": "3"
  },
  {
    "id": "43974",
    "rank": "2440",
    "workers": "600",
    "company": "Quality Floorshine",
    "url": "quality-floorshine",
    "state_l": "New York",
    "state_s": "NY",
    "city": "Brooklyn",
    "growth": "147.0087",
    "revenue": "10759754",
    "ifmid": "9",
    "ifiid": "23",
    "metro": "New York City",
    "industry": "Environmental Services",
    "yrs_on_list": "1"
  },
  {
    "id": "2213",
    "rank": "2452",
    "workers": "660",
    "company": "Digital Insurance",
    "url": "digital-insurance",
    "state_l": "Georgia",
    "state_s": "GA",
    "city": "Atlanta",
    "growth": "145.9211",
    "revenue": "116451000",
    "ifmid": "29",
    "ifiid": "1",
    "metro": "Atlanta",
    "industry": "Insurance",
    "yrs_on_list": "10"
  },
  {
    "id": "423",
    "rank": "2476",
    "workers": "18000",
    "company": "PeopleShare",
    "url": "peopleshare",
    "state_l": "Pennsylvania",
    "state_s": "PA",
    "city": "Pottstown",
    "growth": "144.1915",
    "revenue": "105857679",
    "ifmid": "112",
    "ifiid": "21",
    "metro": "Reading, PA",
    "industry": "Human Resources",
    "yrs_on_list": "8"
  },
  {
    "id": "37903",
    "rank": "2489",
    "workers": "701",
    "company": "PT Solutions Physical Therapy",
    "url": "pt-solutions-physical-therapy",
    "state_l": "Georgia",
    "state_s": "GA",
    "city": "Kennesaw",
    "growth": "143.5004",
    "revenue": "44811706",
    "ifmid": "29",
    "ifiid": "10",
    "metro": "Atlanta",
    "industry": "Health",
    "yrs_on_list": "2"
  },
  {
    "id": "22838",
    "rank": "2500",
    "workers": "600",
    "company": "Partner Engineering and Science",
    "url": "partner-engineering-science",
    "state_l": "California",
    "state_s": "CA",
    "city": "Torrance",
    "growth": "142.5925",
    "revenue": "97005018",
    "ifmid": "2",
    "ifiid": "23",
    "metro": "Los Angeles",
    "industry": "Environmental Services",
    "yrs_on_list": "3"
  },
  {
    "id": "26600",
    "rank": "2565",
    "workers": "6500",
    "company": "Effex Management Solutions",
    "url": "effex-management-solutions",
    "state_l": "Texas",
    "state_s": "TX",
    "city": "Kingwood",
    "growth": "138.1829",
    "revenue": "143720110",
    "ifmid": "22",
    "ifiid": "21",
    "metro": "Houston",
    "industry": "Human Resources",
    "yrs_on_list": "3"
  },
  {
    "id": "2482",
    "rank": "2567",
    "workers": "835",
    "company": "Big Ass Fans",
    "url": "big-ass-fans",
    "state_l": "Kentucky",
    "state_s": "KY",
    "city": "LEXINGTON",
    "growth": "137.9534",
    "revenue": "206710098",
    "ifmid": "132",
    "ifiid": "15",
    "metro": "Lexington-Fayette, KY",
    "industry": "Manufacturing",
    "yrs_on_list": "10"
  },
  {
    "id": "23448",
    "rank": "2572",
    "workers": "819",
    "company": "HCTec Partners",
    "url": "hctec-partners",
    "state_l": "Tennessee",
    "state_s": "TN",
    "city": "Franklin",
    "growth": "137.2974",
    "revenue": "114481572",
    "ifmid": "82",
    "ifiid": "10",
    "metro": "Nashville",
    "industry": "Health",
    "yrs_on_list": "3"
  },
  {
    "id": "26533",
    "rank": "2605",
    "workers": "40000",
    "company": "AtWork Group",
    "url": "atwork-group",
    "state_l": "Tennessee",
    "state_s": "TN",
    "city": "Knoxville",
    "growth": "135.5429",
    "revenue": "257354490",
    "ifmid": "99",
    "ifiid": "21",
    "metro": "Knoxville, TN",
    "industry": "Human Resources",
    "yrs_on_list": "3"
  },
  {
    "id": "18324",
    "rank": "2620",
    "workers": "884",
    "company": "Trinity Solar",
    "url": "trinity-solar",
    "state_l": "New Jersey",
    "state_s": "NJ",
    "city": "Wall",
    "growth": "134.624",
    "revenue": "167979716",
    "ifmid": "9",
    "ifiid": "16",
    "metro": "New York City",
    "industry": "Energy",
    "yrs_on_list": "4"
  },
  {
    "id": "1146",
    "rank": "2634",
    "workers": "1276",
    "company": "Consumer Cellular",
    "url": "consumer-cellular",
    "state_l": "Oregon",
    "state_s": "OR",
    "city": "Portland",
    "growth": "133.7187",
    "revenue": "614984000",
    "ifmid": "10",
    "ifiid": "14",
    "metro": "Portland, OR",
    "industry": "Telecommunications",
    "yrs_on_list": "8"
  },
  {
    "id": "18103",
    "rank": "2642",
    "workers": "1608",
    "company": "DataArt",
    "url": "dataart",
    "state_l": "New York",
    "state_s": "NY",
    "city": "New York",
    "growth": "133.3452",
    "revenue": "71540463",
    "ifmid": "9",
    "ifiid": "9",
    "metro": "New York City",
    "industry": "Software",
    "yrs_on_list": "7"
  },
  {
    "id": "44036",
    "rank": "2643",
    "workers": "2000",
    "company": "Spectraforce",
    "url": "spectraforce",
    "state_l": "North Carolina",
    "state_s": "NC",
    "city": "Raleigh",
    "growth": "133.3078",
    "revenue": "82394232",
    "ifmid": "1029",
    "ifiid": "21",
    "metro": "Raleigh, NC",
    "industry": "Human Resources",
    "yrs_on_list": "1"
  },
  {
    "id": "20995",
    "rank": "2650",
    "workers": "650",
    "company": "Accolade",
    "url": "accolade",
    "state_l": "Pennsylvania",
    "state_s": "PA",
    "city": "Plymouth Meeting",
    "growth": "132.9353",
    "revenue": "74707000",
    "ifmid": "49",
    "ifiid": "10",
    "metro": "Philadelphia",
    "industry": "Health",
    "yrs_on_list": "3"
  },
  {
    "id": "19546",
    "rank": "2682",
    "workers": "625",
    "company": "Butterfly Effects",
    "url": "butterfly-effects",
    "state_l": "Florida",
    "state_s": "FL",
    "city": "Deerfield Beach",
    "growth": "130.7952",
    "revenue": "16668048",
    "ifmid": "1",
    "ifiid": "10",
    "metro": "Miami",
    "industry": "Health",
    "yrs_on_list": "6"
  },
  {
    "id": "25040",
    "rank": "2693",
    "workers": "775",
    "company": "TEC Group",
    "url": "tec-group",
    "state_l": "Michigan",
    "state_s": "MI",
    "city": "Troy",
    "growth": "130.3831",
    "revenue": "74618873",
    "ifmid": "50",
    "ifiid": "21",
    "metro": "Detroit",
    "industry": "Human Resources",
    "yrs_on_list": "3"
  },
  {
    "id": "24919",
    "rank": "2707",
    "workers": "1004",
    "company": "Peak Campus",
    "url": "peak-campus",
    "state_l": "Georgia",
    "state_s": "GA",
    "city": "Atlanta",
    "growth": "129.6331",
    "revenue": "15311926",
    "ifmid": "29",
    "ifiid": "3",
    "metro": "Atlanta",
    "industry": "Real Estate",
    "yrs_on_list": "3"
  },
  {
    "id": "22377",
    "rank": "2738",
    "workers": "829",
    "company": "Linium",
    "url": "linium",
    "state_l": "New York",
    "state_s": "NY",
    "city": "New York",
    "growth": "127.9758",
    "revenue": "102430347",
    "ifmid": "9",
    "ifiid": "17",
    "metro": "New York City",
    "industry": "Business Products & Services",
    "yrs_on_list": "5"
  },
  {
    "id": "21510",
    "rank": "2741",
    "workers": "1336",
    "company": "Supreme Lending",
    "url": "supreme-lending",
    "state_l": "Texas",
    "state_s": "TX",
    "city": "Dallas",
    "growth": "127.7479",
    "revenue": "306498012",
    "ifmid": "8",
    "ifiid": "2",
    "metro": "Dallas",
    "industry": "Financial Services",
    "yrs_on_list": "5"
  },
  {
    "id": "22504",
    "rank": "2753",
    "workers": "2217",
    "company": "Orion Associates",
    "url": "orion-associates",
    "state_l": "Minnesota",
    "state_s": "MN",
    "city": "Golden Valley",
    "growth": "127.2019",
    "revenue": "112361817",
    "ifmid": "13",
    "ifiid": "21",
    "metro": "Minneapolis",
    "industry": "Human Resources",
    "yrs_on_list": "4"
  },
  {
    "id": "37250",
    "rank": "2775",
    "workers": "600",
    "company": "IntuitiveHRO",
    "url": "intuitivehro",
    "state_l": "Arizona",
    "state_s": "AZ",
    "city": "Tempe",
    "growth": "126.0167",
    "revenue": "18962942",
    "ifmid": "46",
    "ifiid": "21",
    "metro": "Phoenix",
    "industry": "Human Resources",
    "yrs_on_list": "2"
  },
  {
    "id": "44073",
    "rank": "2780",
    "workers": "1782",
    "company": "Virtual Properties Realty",
    "url": "virtual-properties-realty",
    "state_l": "Georgia",
    "state_s": "GA",
    "city": "Duluth",
    "growth": "125.6554",
    "revenue": "3971580",
    "ifmid": "29",
    "ifiid": "3",
    "metro": "Atlanta",
    "industry": "Real Estate",
    "yrs_on_list": "1"
  },
  {
    "id": "3725",
    "rank": "2792",
    "workers": "2000",
    "company": "CyraCom",
    "url": "cyracom",
    "state_l": "Arizona",
    "state_s": "AZ",
    "city": "Tucson",
    "growth": "125.1274",
    "revenue": "109634535",
    "ifmid": "154",
    "ifiid": "17",
    "metro": "Tucson, AZ",
    "industry": "Business Products & Services",
    "yrs_on_list": "10"
  },
  {
    "id": "44085",
    "rank": "2815",
    "workers": "980",
    "company": "Wilson-Bennett Technology",
    "url": "wilson-bennett-technology",
    "state_l": "Arkansas",
    "state_s": "AR",
    "city": "Cabot",
    "growth": "123.8729",
    "revenue": "4835982",
    "ifmid": "122",
    "ifiid": "17",
    "metro": "Little Rock-North Little Rock-Conway, AR",
    "industry": "Business Products & Services",
    "yrs_on_list": "1"
  },
  {
    "id": "854",
    "rank": "2819",
    "workers": "2000",
    "company": "Monogram Foods",
    "url": "monogram-foods",
    "state_l": "Tennessee",
    "state_s": "TN",
    "city": "Memphis",
    "growth": "123.7465",
    "revenue": "442122010",
    "ifmid": "105",
    "ifiid": "11",
    "metro": "Memphis, TN-MS-AR",
    "industry": "Food & Beverage",
    "yrs_on_list": "8"
  },
  {
    "id": "44091",
    "rank": "2831",
    "workers": "1941",
    "company": "Comprehensive Logisitcs Co.",
    "url": "comprehensive-logisitcs-co",
    "state_l": "Ohio",
    "state_s": "OH",
    "city": "Youngstown",
    "growth": "122.8793",
    "revenue": "175706165",
    "ifmid": "168",
    "ifiid": "6",
    "metro": "Youngstown-Warren-Boardman, OH-PA",
    "industry": "Logistics & Transportation",
    "yrs_on_list": "1"
  },
  {
    "id": "18097",
    "rank": "2835",
    "workers": "846",
    "company": "Keller Williams Capital Properties",
    "url": "keller-williams-capital-properties",
    "state_l": "District of Columbia",
    "state_s": "DC",
    "city": "Washington",
    "growth": "122.8121",
    "revenue": "52755997",
    "ifmid": "3",
    "ifiid": "3",
    "metro": "Washington, DC",
    "industry": "Real Estate",
    "yrs_on_list": "7"
  },
  {
    "id": "8181",
    "rank": "2893",
    "workers": "15390",
    "company": "Peoplelink",
    "url": "peoplelink",
    "state_l": "Indiana",
    "state_s": "IN",
    "city": "south bend",
    "growth": "119.3756",
    "revenue": "318215500",
    "ifmid": "142",
    "ifiid": "21",
    "metro": "South Bend-Mishawaka, IN-MI",
    "industry": "Human Resources",
    "yrs_on_list": "6"
  },
  {
    "id": "20220",
    "rank": "2894",
    "workers": "1502",
    "company": "ProTransport-1",
    "url": "protransport-1",
    "state_l": "California",
    "state_s": "CA",
    "city": "Cotati",
    "growth": "119.3546",
    "revenue": "82420835",
    "ifmid": "1025",
    "ifiid": "10",
    "metro": "Santa Rosa, CA",
    "industry": "Health",
    "yrs_on_list": "6"
  },
  {
    "id": "1887",
    "rank": "2895",
    "workers": "957",
    "company": "Elwood Staffing",
    "url": "elwood-staffing",
    "state_l": "Indiana",
    "state_s": "IN",
    "city": "Columbus",
    "growth": "119.3549",
    "revenue": "804291000",
    "ifmid": "223",
    "ifiid": "21",
    "metro": "Columbus, IN",
    "industry": "Human Resources",
    "yrs_on_list": "8"
  },
  {
    "id": "17768",
    "rank": "2900",
    "workers": "1600",
    "company": "Power Home Remodeling",
    "url": "power-home-remodeling",
    "state_l": "Pennsylvania",
    "state_s": "PA",
    "city": "Chester",
    "growth": "119.1514",
    "revenue": "366959291",
    "ifmid": "49",
    "ifiid": "20",
    "metro": "Philadelphia",
    "industry": "Construction",
    "yrs_on_list": "7"
  },
  {
    "id": "25244",
    "rank": "2923",
    "workers": "6000",
    "company": "The Greene Group",
    "url": "the-greene-group",
    "state_l": "North Carolina",
    "state_s": "NC",
    "city": "Davidson",
    "growth": "117.5958",
    "revenue": "49917724",
    "ifmid": "43",
    "ifiid": "21",
    "metro": "Charlotte",
    "industry": "Human Resources",
    "yrs_on_list": "3"
  },
  {
    "id": "44115",
    "rank": "2926",
    "workers": "5000",
    "company": "Studio Movie Grill",
    "url": "studio-movie-grill",
    "state_l": "Texas",
    "state_s": "TX",
    "city": "Dallas",
    "growth": "117.4501",
    "revenue": "161361000",
    "ifmid": "8",
    "ifiid": "11",
    "metro": "Dallas",
    "industry": "Food & Beverage",
    "yrs_on_list": "1"
  },
  {
    "id": "3852",
    "rank": "2928",
    "workers": "4244",
    "company": "DTI",
    "url": "dti",
    "state_l": "Georgia",
    "state_s": "GA",
    "city": "Atlanta",
    "growth": "117.2885",
    "revenue": "407006847",
    "ifmid": "29",
    "ifiid": "17",
    "metro": "Atlanta",
    "industry": "Business Products & Services",
    "yrs_on_list": "9"
  },
  {
    "id": "21853",
    "rank": "2937",
    "workers": "829",
    "company": "ADVANCED DISCOVERY",
    "url": "advanced-discovery",
    "state_l": "Texas",
    "state_s": "TX",
    "city": "AUSTIN",
    "growth": "117.0686",
    "revenue": "71645662",
    "ifmid": "18",
    "ifiid": "17",
    "metro": "Austin",
    "industry": "Business Products & Services",
    "yrs_on_list": "5"
  },
  {
    "id": "44121",
    "rank": "2942",
    "workers": "1920",
    "company": "JobFinders Employment Services",
    "url": "jobfinders-employment-services",
    "state_l": "Missouri",
    "state_s": "MO",
    "city": "Columbia",
    "growth": "116.6985",
    "revenue": "9139538",
    "ifmid": "62",
    "ifiid": "21",
    "metro": "Columbia, MO",
    "industry": "Human Resources",
    "yrs_on_list": "1"
  },
  {
    "id": "23820",
    "rank": "2943",
    "workers": "2775",
    "company": "Cooper's Hawk Winery & Restaurants",
    "url": "coopers-hawk-winery-restaurants",
    "state_l": "Illinois",
    "state_s": "IL",
    "city": "Countryside",
    "growth": "116.6293",
    "revenue": "147856000",
    "ifmid": "17",
    "ifiid": "11",
    "metro": "Chicago",
    "industry": "Food & Beverage",
    "yrs_on_list": "4"
  },
  {
    "id": "44122",
    "rank": "2944",
    "workers": "750",
    "company": "Namecheap",
    "url": "namecheap",
    "state_l": "California",
    "state_s": "CA",
    "city": "Los Angeles",
    "growth": "116.5402",
    "revenue": "76024946",
    "ifmid": "2",
    "ifiid": "8",
    "metro": "Los Angeles",
    "industry": "IT Services",
    "yrs_on_list": "1"
  },
  {
    "id": "38151",
    "rank": "2950",
    "workers": "1200",
    "company": "Moon Valley Nurseries",
    "url": "moon-valley-nurseries",
    "state_l": "Arizona",
    "state_s": "AZ",
    "city": "Phoenix",
    "growth": "116.1275",
    "revenue": "96868307",
    "ifmid": "46",
    "ifiid": "20",
    "metro": "Phoenix",
    "industry": "Construction",
    "yrs_on_list": "2"
  },
  {
    "id": "21133",
    "rank": "2963",
    "workers": "5000",
    "company": "FCi Federal",
    "url": "fci-federal",
    "state_l": "Virginia",
    "state_s": "VA",
    "city": "Ashburn",
    "growth": "115.6214",
    "revenue": "152792445",
    "ifmid": "3",
    "ifiid": "7",
    "metro": "Washington, DC",
    "industry": "Government Services",
    "yrs_on_list": "5"
  },
  {
    "id": "18577",
    "rank": "2969",
    "workers": "1250",
    "company": "O2 Fitness",
    "url": "o2-fitness",
    "state_l": "North Carolina",
    "state_s": "NC",
    "city": "Raleigh",
    "growth": "115.4434",
    "revenue": "28720213",
    "ifmid": "1029",
    "ifiid": "10",
    "metro": "Raleigh, NC",
    "industry": "Health",
    "yrs_on_list": "7"
  },
  {
    "id": "805",
    "rank": "2979",
    "workers": "1203",
    "company": "Hargrove Engineers + Constructors",
    "url": "hargrove-engineers-constructors",
    "state_l": "Alabama",
    "state_s": "AL",
    "city": "Mobile",
    "growth": "114.9007",
    "revenue": "176729373",
    "ifmid": "136",
    "ifiid": "24",
    "metro": "Mobile, AL",
    "industry": "Engineering",
    "yrs_on_list": "9"
  },
  {
    "id": "44142",
    "rank": "3013",
    "workers": "1250",
    "company": "LDV Hospitality Management",
    "url": "ldv-hospitality-management",
    "state_l": "New York",
    "state_s": "NY",
    "city": "New York",
    "growth": "113.5565",
    "revenue": "65793056",
    "ifmid": "9",
    "ifiid": "11",
    "metro": "New York City",
    "industry": "Food & Beverage",
    "yrs_on_list": "1"
  },
  {
    "id": "22394",
    "rank": "3023",
    "workers": "3936",
    "company": "Prime Therapeutics",
    "url": "prime-therapeutics",
    "state_l": "Minnesota",
    "state_s": "MN",
    "city": "Eagan",
    "growth": "113.2428",
    "revenue": "4355582000",
    "ifmid": "13",
    "ifiid": "10",
    "metro": "Minneapolis",
    "industry": "Health",
    "yrs_on_list": "5"
  },
  {
    "id": "9734",
    "rank": "3025",
    "workers": "4718",
    "company": "DriveTIme",
    "url": "drivetime",
    "state_l": "Arizona",
    "state_s": "AZ",
    "city": "Tempe",
    "growth": "113.0903",
    "revenue": "2607298000",
    "ifmid": "46",
    "ifiid": "4",
    "metro": "Phoenix",
    "industry": "Consumer Products & Services",
    "yrs_on_list": "3"
  },
  {
    "id": "25010",
    "rank": "3070",
    "workers": "850",
    "company": "DataBank IMX",
    "url": "databank-imx",
    "state_l": "Pennsylvania",
    "state_s": "PA",
    "city": "King of Prussia",
    "growth": "110.8075",
    "revenue": "99254343",
    "ifmid": "49",
    "ifiid": "8",
    "metro": "Philadelphia",
    "industry": "IT Services",
    "yrs_on_list": "3"
  },
  {
    "id": "1616",
    "rank": "3085",
    "workers": "1120",
    "company": "Stone Brewing Co.",
    "url": "stone-brewing-co",
    "state_l": "California",
    "state_s": "CA",
    "city": "Escondido",
    "growth": "110.0639",
    "revenue": "217106344",
    "ifmid": "11",
    "ifiid": "11",
    "metro": "San Diego",
    "industry": "Food & Beverage",
    "yrs_on_list": "12"
  },
  {
    "id": "25790",
    "rank": "3105",
    "workers": "2137",
    "company": "SRS Distribution",
    "url": "srs-distribution",
    "state_l": "Texas",
    "state_s": "TX",
    "city": "McKinney",
    "growth": "109.5146",
    "revenue": "1411018720",
    "ifmid": "8",
    "ifiid": "4",
    "metro": "Dallas",
    "industry": "Consumer Products & Services",
    "yrs_on_list": "3"
  },
  {
    "id": "25307",
    "rank": "3120",
    "workers": "697",
    "company": "Atlanta Communities Real Estate Brokerage",
    "url": "atlanta-communities-real-estate-brokerage",
    "state_l": "Georgia",
    "state_s": "GA",
    "city": "Marietta",
    "growth": "108.5671",
    "revenue": "37230046",
    "ifmid": "29",
    "ifiid": "3",
    "metro": "Atlanta",
    "industry": "Real Estate",
    "yrs_on_list": "3"
  },
  {
    "id": "37325",
    "rank": "3122",
    "workers": "1021",
    "company": "American Financial Network",
    "url": "american-financial-network",
    "state_l": "California",
    "state_s": "CA",
    "city": "Brea",
    "growth": "108.5158",
    "revenue": "142640446",
    "ifmid": "2",
    "ifiid": "2",
    "metro": "Los Angeles",
    "industry": "Financial Services",
    "yrs_on_list": "2"
  },
  {
    "id": "44156",
    "rank": "3124",
    "workers": "1875",
    "company": "Student Painters",
    "url": "student-painters",
    "state_l": "Michigan",
    "state_s": "MI",
    "city": "Shelby Twp",
    "growth": "108.388",
    "revenue": "7304000",
    "ifmid": "50",
    "ifiid": "4",
    "metro": "Detroit",
    "industry": "Consumer Products & Services",
    "yrs_on_list": "1"
  },
  {
    "id": "37988",
    "rank": "3157",
    "workers": "954",
    "company": "hire priority",
    "url": "hire-priority",
    "state_l": "Texas",
    "state_s": "TX",
    "city": "Austin",
    "growth": "106.9154",
    "revenue": "4132399",
    "ifmid": "18",
    "ifiid": "21",
    "metro": "Austin",
    "industry": "Human Resources",
    "yrs_on_list": "2"
  },
  {
    "id": "24051",
    "rank": "3168",
    "workers": "864",
    "company": "ACCESS Destination Services",
    "url": "access-destination-services",
    "state_l": "California",
    "state_s": "CA",
    "city": "San Diego",
    "growth": "106.2624",
    "revenue": "92651653",
    "ifmid": "11",
    "ifiid": "22",
    "metro": "San Diego",
    "industry": "Travel & Hospitality",
    "yrs_on_list": "4"
  },
  {
    "id": "12595",
    "rank": "3188",
    "workers": "1550",
    "company": "Compunnel Software Group",
    "url": "compunnel-software-group",
    "state_l": "New Jersey",
    "state_s": "NJ",
    "city": "Plainsboro",
    "growth": "105.4659",
    "revenue": "108815365",
    "ifmid": "9",
    "ifiid": "8",
    "metro": "New York City",
    "industry": "IT Services",
    "yrs_on_list": "6"
  },
  {
    "id": "21245",
    "rank": "3202",
    "workers": "1738",
    "company": "DMI",
    "url": "dmi",
    "state_l": "Maryland",
    "state_s": "MD",
    "city": "Bethesda",
    "growth": "104.7266",
    "revenue": "332547087",
    "ifmid": "3",
    "ifiid": "8",
    "metro": "Washington, DC",
    "industry": "IT Services",
    "yrs_on_list": "10"
  },
  {
    "id": "57",
    "rank": "3207",
    "workers": "2454",
    "company": "ReSource Pro",
    "url": "resource-pro",
    "state_l": "New York",
    "state_s": "NY",
    "city": "NEW YORK",
    "growth": "104.3185",
    "revenue": "49597079",
    "ifmid": "9",
    "ifiid": "1",
    "metro": "New York City",
    "industry": "Insurance",
    "yrs_on_list": "8"
  },
  {
    "id": "22219",
    "rank": "3209",
    "workers": "1300",
    "company": "Apple Bus Company",
    "url": "apple-bus-company",
    "state_l": "Missouri",
    "state_s": "MO",
    "city": "Cleveland",
    "growth": "104.3072",
    "revenue": "44158958",
    "ifmid": "21",
    "ifiid": "6",
    "metro": "Kansas City, MO-KS",
    "industry": "Logistics & Transportation",
    "yrs_on_list": "4"
  },
  {
    "id": "22867",
    "rank": "3236",
    "workers": "1663",
    "company": "Software Paradigms International Group",
    "url": "software-paradigms-international-group",
    "state_l": "Georgia",
    "state_s": "GA",
    "city": "Atlanta",
    "growth": "103.2414",
    "revenue": "83586835",
    "ifmid": "29",
    "ifiid": "8",
    "metro": "Atlanta",
    "industry": "IT Services",
    "yrs_on_list": "8"
  },
  {
    "id": "4027",
    "rank": "3261",
    "workers": "1000",
    "company": "Arrow Security",
    "url": "arrow-security",
    "state_l": "New York",
    "state_s": "NY",
    "city": "Smithtown",
    "growth": "102.3252",
    "revenue": "27897592",
    "ifmid": "9",
    "ifiid": "13",
    "metro": "New York City",
    "industry": "Security",
    "yrs_on_list": "4"
  },
  {
    "id": "25807",
    "rank": "3288",
    "workers": "658",
    "company": "First Guaranty Mortgage",
    "url": "first-guaranty-mortgage",
    "state_l": "Virginia",
    "state_s": "VA",
    "city": "Tysons Corner",
    "growth": "100.9331",
    "revenue": "99876284",
    "ifmid": "3",
    "ifiid": "2",
    "metro": "Washington, DC",
    "industry": "Financial Services",
    "yrs_on_list": "3"
  },
  {
    "id": "787",
    "rank": "3334",
    "workers": "15316",
    "company": "Insight Global",
    "url": "insight-global",
    "state_l": "Georgia",
    "state_s": "GA",
    "city": "Atlanta",
    "growth": "98.8232",
    "revenue": "1483826894",
    "ifmid": "29",
    "ifiid": "8",
    "metro": "Atlanta",
    "industry": "IT Services",
    "yrs_on_list": "9"
  },
  {
    "id": "22092",
    "rank": "3357",
    "workers": "5500",
    "company": "Home Care Assistance",
    "url": "home-care-assistance",
    "state_l": "California",
    "state_s": "CA",
    "city": "Palo Alto",
    "growth": "97.9217",
    "revenue": "124071604",
    "ifmid": "20",
    "ifiid": "10",
    "metro": "San Jose",
    "industry": "Health",
    "yrs_on_list": "5"
  },
  {
    "id": "25110",
    "rank": "3370",
    "workers": "693",
    "company": "GENEWIZ",
    "url": "genewiz",
    "state_l": "New Jersey",
    "state_s": "NJ",
    "city": "South Plainfield",
    "growth": "97.5824",
    "revenue": "65709485",
    "ifmid": "9",
    "ifiid": "10",
    "metro": "New York City",
    "industry": "Health",
    "yrs_on_list": "3"
  },
  {
    "id": "3153",
    "rank": "3372",
    "workers": "609",
    "company": "V-Soft Consulting Group",
    "url": "v-soft-consulting-group",
    "state_l": "Kentucky",
    "state_s": "KY",
    "city": "Louisville",
    "growth": "97.313",
    "revenue": "71878349",
    "ifmid": "630",
    "ifiid": "8",
    "metro": "Louisville/Jefferson County, KY-IN",
    "industry": "IT Services",
    "yrs_on_list": "10"
  },
  {
    "id": "4316",
    "rank": "3373",
    "workers": "65531",
    "company": "Integrity Staffing Solutions",
    "url": "integrity-staffing-solutions",
    "state_l": "Delaware",
    "state_s": "DE",
    "city": "Newark",
    "growth": "97.2691",
    "revenue": "549086411",
    "ifmid": "49",
    "ifiid": "21",
    "metro": "Philadelphia",
    "industry": "Human Resources",
    "yrs_on_list": "12"
  },
  {
    "id": "44221",
    "rank": "3375",
    "workers": "1512",
    "company": "Optiv Security",
    "url": "optiv-security",
    "state_l": "Colorado",
    "state_s": "CO",
    "city": "Denver",
    "growth": "97.0888",
    "revenue": "1882429001",
    "ifmid": "30",
    "ifiid": "13",
    "metro": "Denver",
    "industry": "Security",
    "yrs_on_list": "1"
  },
  {
    "id": "44226",
    "rank": "3396",
    "workers": "700",
    "company": "Acuative",
    "url": "acuative",
    "state_l": "New Jersey",
    "state_s": "NJ",
    "city": "Fairfield",
    "growth": "96.191",
    "revenue": "120194701",
    "ifmid": "9",
    "ifiid": "8",
    "metro": "New York City",
    "industry": "IT Services",
    "yrs_on_list": "1"
  },
  {
    "id": "44228",
    "rank": "3402",
    "workers": "600",
    "company": "Aubree's Pizzeria & Grill",
    "url": "aubrees-pizzeria-grill",
    "state_l": "Michigan",
    "state_s": "MI",
    "city": "Ann Arbor",
    "growth": "95.941",
    "revenue": "16818600",
    "ifmid": "84",
    "ifiid": "11",
    "metro": "Ann Arbor, MI",
    "industry": "Food & Beverage",
    "yrs_on_list": "1"
  },
  {
    "id": "44229",
    "rank": "3403",
    "workers": "1100",
    "company": "Tri-City Electric Company of Iowa",
    "url": "tri-city-electric-company-of-iowa",
    "state_l": "Iowa",
    "state_s": "IA",
    "city": "Davenport",
    "growth": "95.9436",
    "revenue": "155227906",
    "ifmid": "37",
    "ifiid": "20",
    "metro": "Davenport-Moline-Rock Island, IA-IL",
    "industry": "Construction",
    "yrs_on_list": "1"
  },
  {
    "id": "44230",
    "rank": "3405",
    "workers": "1300",
    "company": "Kneaders Bakery and Cafe",
    "url": "kneaders-bakery-and-cafe",
    "state_l": "Utah",
    "state_s": "UT",
    "city": "Orem",
    "growth": "95.8595",
    "revenue": "77736653",
    "ifmid": "48",
    "ifiid": "11",
    "metro": "Provo-Orem, UT",
    "industry": "Food & Beverage",
    "yrs_on_list": "1"
  },
  {
    "id": "21827",
    "rank": "3440",
    "workers": "800",
    "company": "Fractal Analytics",
    "url": "fractal-analytics",
    "state_l": "California",
    "state_s": "CA",
    "city": "San Mateo",
    "growth": "94.1838",
    "revenue": "33191438",
    "ifmid": "4",
    "ifiid": "17",
    "metro": "San Francisco",
    "industry": "Business Products & Services",
    "yrs_on_list": "5"
  },
  {
    "id": "4936",
    "rank": "3452",
    "workers": "9334",
    "company": "Prestige Employee Administrators",
    "url": "prestige-employee-administrators",
    "state_l": "New York",
    "state_s": "NY",
    "city": "Melville",
    "growth": "93.7034",
    "revenue": "891228173",
    "ifmid": "9",
    "ifiid": "21",
    "metro": "New York City",
    "industry": "Human Resources",
    "yrs_on_list": "7"
  },
  {
    "id": "44248",
    "rank": "3488",
    "workers": "792",
    "company": "Charter Global",
    "url": "charter-global",
    "state_l": "Georgia",
    "state_s": "GA",
    "city": "Atlanta",
    "growth": "91.2883",
    "revenue": "33468087",
    "ifmid": "29",
    "ifiid": "8",
    "metro": "Atlanta",
    "industry": "IT Services",
    "yrs_on_list": "1"
  },
  {
    "id": "21536",
    "rank": "3503",
    "workers": "749",
    "company": "Zenetex",
    "url": "zenetex",
    "state_l": "Virginia",
    "state_s": "VA",
    "city": "Herndon",
    "growth": "90.3322",
    "revenue": "84303262",
    "ifmid": "3",
    "ifiid": "7",
    "metro": "Washington, DC",
    "industry": "Government Services",
    "yrs_on_list": "5"
  },
  {
    "id": "44253",
    "rank": "3515",
    "workers": "736",
    "company": "Citywide Home Loans",
    "url": "citywide-home-loans",
    "state_l": "Utah",
    "state_s": "UT",
    "city": "Sandy",
    "growth": "89.7737",
    "revenue": "97387475",
    "ifmid": "12",
    "ifiid": "3",
    "metro": "Salt Lake City",
    "industry": "Real Estate",
    "yrs_on_list": "1"
  },
  {
    "id": "44265",
    "rank": "3559",
    "workers": "906",
    "company": "Power Design",
    "url": "power-design",
    "state_l": "Florida",
    "state_s": "FL",
    "city": "St. Petersburg",
    "growth": "88.6521",
    "revenue": "266058936",
    "ifmid": "7",
    "ifiid": "20",
    "metro": "Tampa",
    "industry": "Construction",
    "yrs_on_list": "1"
  },
  {
    "id": "24807",
    "rank": "3583",
    "workers": "1111",
    "company": "Express Locations",
    "url": "express-locations",
    "state_l": "Washington",
    "state_s": "WA",
    "city": "Wenatchee",
    "growth": "87.4611",
    "revenue": "94955628",
    "ifmid": "970",
    "ifiid": "18",
    "metro": "Wenatchee, WA",
    "industry": "Retail",
    "yrs_on_list": "3"
  },
  {
    "id": "65",
    "rank": "3595",
    "workers": "740",
    "company": "Lifematters",
    "url": "lifematters",
    "state_l": "Maryland",
    "state_s": "MD",
    "city": "Bethesda",
    "growth": "87.0941",
    "revenue": "22378680",
    "ifmid": "3",
    "ifiid": "10",
    "metro": "Washington, DC",
    "industry": "Health",
    "yrs_on_list": "8"
  },
  {
    "id": "2887",
    "rank": "3617",
    "workers": "4537",
    "company": "Program Productions",
    "url": "program-productions",
    "state_l": "Illinois",
    "state_s": "IL",
    "city": "Lombard",
    "growth": "86.245",
    "revenue": "38517945",
    "ifmid": "17",
    "ifiid": "12",
    "metro": "Chicago",
    "industry": "Media",
    "yrs_on_list": "10"
  },
  {
    "id": "26169",
    "rank": "3618",
    "workers": "5838",
    "company": "College Nannies, Sitters and Tutors",
    "url": "college-nannies-sitters-and-tutors",
    "state_l": "Minnesota",
    "state_s": "MN",
    "city": "Minneapolis",
    "growth": "86.2259",
    "revenue": "3338937",
    "ifmid": "13",
    "ifiid": "4",
    "metro": "Minneapolis",
    "industry": "Consumer Products & Services",
    "yrs_on_list": "3"
  },
  {
    "id": "19489",
    "rank": "3692",
    "workers": "746",
    "company": "Maximum One Realty",
    "url": "maximum-one-realty",
    "state_l": "Georgia",
    "state_s": "GA",
    "city": "Atlanta",
    "growth": "83.8754",
    "revenue": "15909785",
    "ifmid": "29",
    "ifiid": "3",
    "metro": "Atlanta",
    "industry": "Real Estate",
    "yrs_on_list": "6"
  },
  {
    "id": "38080",
    "rank": "3700",
    "workers": "610",
    "company": "CareHere",
    "url": "carehere",
    "state_l": "Tennessee",
    "state_s": "TN",
    "city": "Brentwood",
    "growth": "83.5242",
    "revenue": "94343604",
    "ifmid": "82",
    "ifiid": "10",
    "metro": "Nashville",
    "industry": "Health",
    "yrs_on_list": "2"
  },
  {
    "id": "22854",
    "rank": "3715",
    "workers": "750",
    "company": "WMK",
    "url": "wmk",
    "state_l": "Ohio",
    "state_s": "OH",
    "city": "Richfield",
    "growth": "82.9399",
    "revenue": "239571980",
    "ifmid": "34",
    "ifiid": "18",
    "metro": "Akron, OH",
    "industry": "Retail",
    "yrs_on_list": "11"
  },
  {
    "id": "37965",
    "rank": "3727",
    "workers": "614",
    "company": "Maser Consulting",
    "url": "maser-consulting",
    "state_l": "New Jersey",
    "state_s": "NJ",
    "city": "Red Bank",
    "growth": "82.493",
    "revenue": "89458786",
    "ifmid": "9",
    "ifiid": "24",
    "metro": "New York City",
    "industry": "Engineering",
    "yrs_on_list": "2"
  },
  {
    "id": "10890",
    "rank": "3753",
    "workers": "8493",
    "company": "Heartland Dental",
    "url": "heartland-dental",
    "state_l": "Illinois",
    "state_s": "IL",
    "city": "Effingham",
    "growth": "81.6102",
    "revenue": "1018413264",
    "ifmid": "428",
    "ifiid": "17",
    "metro": "Effingham, IL",
    "industry": "Business Products & Services",
    "yrs_on_list": "6"
  },
  {
    "id": "2567",
    "rank": "3864",
    "workers": "1091",
    "company": "PEOPLE'S CARE HOLDINGS",
    "url": "peoples-care-holdings",
    "state_l": "California",
    "state_s": "CA",
    "city": "CHINO HILLS",
    "growth": "77.5343",
    "revenue": "42380784",
    "ifmid": "2",
    "ifiid": "10",
    "metro": "Los Angeles",
    "industry": "Health",
    "yrs_on_list": "8"
  },
  {
    "id": "18363",
    "rank": "3905",
    "workers": "774",
    "company": "DiscountMugs.com",
    "url": "discountmugscom",
    "state_l": "Florida",
    "state_s": "FL",
    "city": "Medley",
    "growth": "75.8153",
    "revenue": "135834394",
    "ifmid": "1",
    "ifiid": "17",
    "metro": "Miami",
    "industry": "Business Products & Services",
    "yrs_on_list": "7"
  },
  {
    "id": "26324",
    "rank": "3914",
    "workers": "2000",
    "company": "The Woodhouse Day Spas",
    "url": "the-woodhouse-day-spas",
    "state_l": "Texas",
    "state_s": "TX",
    "city": "Victoria",
    "growth": "75.5843",
    "revenue": "3321352",
    "ifmid": "870",
    "ifiid": "22",
    "metro": "Victoria, TX",
    "industry": "Travel & Hospitality",
    "yrs_on_list": "3"
  },
  {
    "id": "38114",
    "rank": "3915",
    "workers": "609",
    "company": "Single Source",
    "url": "single-source",
    "state_l": "Georgia",
    "state_s": "GA",
    "city": "Roswell",
    "growth": "75.5726",
    "revenue": "202971543",
    "ifmid": "29",
    "ifiid": "17",
    "metro": "Atlanta",
    "industry": "Business Products & Services",
    "yrs_on_list": "2"
  },
  {
    "id": "2630",
    "rank": "3918",
    "workers": "789",
    "company": "ConServe",
    "url": "conserve",
    "state_l": "New York",
    "state_s": "NY",
    "city": "Fairport",
    "growth": "75.3723",
    "revenue": "92684814",
    "ifmid": "71",
    "ifiid": "2",
    "metro": "Rochester, NY",
    "industry": "Financial Services",
    "yrs_on_list": "6"
  },
  {
    "id": "25883",
    "rank": "3977",
    "workers": "1939",
    "company": "MEC",
    "url": "mec",
    "state_l": "Wisconsin",
    "state_s": "WI",
    "city": "Mayville",
    "growth": "73.4978",
    "revenue": "305026368",
    "ifmid": "716",
    "ifiid": "15",
    "metro": "Beaver Dam, WI",
    "industry": "Manufacturing",
    "yrs_on_list": "3"
  },
  {
    "id": "26085",
    "rank": "3989",
    "workers": "725",
    "company": "CT in Home Assistance",
    "url": "ct-in-home-assistance",
    "state_l": "Connecticut",
    "state_s": "CT",
    "city": "Trumbull",
    "growth": "73.0295",
    "revenue": "9002309",
    "ifmid": "58",
    "ifiid": "10",
    "metro": "Bridgeport-Stamford-Norwalk, CT",
    "industry": "Health",
    "yrs_on_list": "3"
  },
  {
    "id": "26099",
    "rank": "3993",
    "workers": "601",
    "company": "KMS Technology",
    "url": "kms-technology",
    "state_l": "Georgia",
    "state_s": "GA",
    "city": "Atlanta",
    "growth": "72.9685",
    "revenue": "17863009",
    "ifmid": "29",
    "ifiid": "8",
    "metro": "Atlanta",
    "industry": "IT Services",
    "yrs_on_list": "3"
  },
  {
    "id": "4075",
    "rank": "4004",
    "workers": "792",
    "company": "Garland Industries",
    "url": "garland-industries",
    "state_l": "Ohio",
    "state_s": "OH",
    "city": "Cleveland",
    "growth": "72.785",
    "revenue": "460931813",
    "ifmid": "79",
    "ifiid": "15",
    "metro": "Cleveland",
    "industry": "Manufacturing",
    "yrs_on_list": "7"
  },
  {
    "id": "2121",
    "rank": "4006",
    "workers": "784",
    "company": "Total Hockey",
    "url": "total-hockey",
    "state_l": "Missouri",
    "state_s": "MO",
    "city": "Maryland Heights",
    "growth": "72.666",
    "revenue": "62037069",
    "ifmid": "74",
    "ifiid": "18",
    "metro": "St. Louis, MO-IL",
    "industry": "Retail",
    "yrs_on_list": "9"
  },
  {
    "id": "3334",
    "rank": "4009",
    "workers": "1168",
    "company": "Shawmut Design and Construction",
    "url": "shawmut-design-and-construction",
    "state_l": "Massachusetts",
    "state_s": "MA",
    "city": "Boston",
    "growth": "72.6194",
    "revenue": "1174310103",
    "ifmid": "6",
    "ifiid": "20",
    "metro": "Boston",
    "industry": "Construction",
    "yrs_on_list": "10"
  },
  {
    "id": "37841",
    "rank": "4030",
    "workers": "750",
    "company": "Keeley Companies",
    "url": "keeley-companies",
    "state_l": "Missouri",
    "state_s": "MO",
    "city": "St. Louis",
    "growth": "71.8187",
    "revenue": "228844023",
    "ifmid": "74",
    "ifiid": "20",
    "metro": "St. Louis, MO-IL",
    "industry": "Construction",
    "yrs_on_list": "2"
  },
  {
    "id": "44372",
    "rank": "4035",
    "workers": "1232",
    "company": "VimHR",
    "url": "vimhr",
    "state_l": "Arizona",
    "state_s": "AZ",
    "city": "Phoenix",
    "growth": "71.71",
    "revenue": "14555460",
    "ifmid": "46",
    "ifiid": "21",
    "metro": "Phoenix",
    "industry": "Human Resources",
    "yrs_on_list": "1"
  },
  {
    "id": "44375",
    "rank": "4050",
    "workers": "1293",
    "company": "InterSolutions",
    "url": "intersolutions",
    "state_l": "New Jersey",
    "state_s": "NJ",
    "city": "Cherry Hill",
    "growth": "71.1847",
    "revenue": "11278922",
    "ifmid": "49",
    "ifiid": "17",
    "metro": "Philadelphia",
    "industry": "Business Products & Services",
    "yrs_on_list": "1"
  },
  {
    "id": "24069",
    "rank": "4064",
    "workers": "30000",
    "company": "PrideStaff",
    "url": "pridestaff",
    "state_l": "California",
    "state_s": "CA",
    "city": "Fresno",
    "growth": "70.6718",
    "revenue": "195063020",
    "ifmid": "345",
    "ifiid": "21",
    "metro": "Fresno, CA",
    "industry": "Human Resources",
    "yrs_on_list": "2"
  },
  {
    "id": "23935",
    "rank": "4070",
    "workers": "27000",
    "company": "Infiniti HR",
    "url": "infiniti-hr",
    "state_l": "Maryland",
    "state_s": "MD",
    "city": "Burtonsville",
    "growth": "70.3789",
    "revenue": "223673497",
    "ifmid": "3",
    "ifiid": "21",
    "metro": "Washington, DC",
    "industry": "Human Resources",
    "yrs_on_list": "4"
  },
  {
    "id": "44387",
    "rank": "4101",
    "workers": "1277",
    "company": "Oceans Healthcare",
    "url": "oceans-healthcare",
    "state_l": "Texas",
    "state_s": "TX",
    "city": "Plano",
    "growth": "69.2795",
    "revenue": "77701000",
    "ifmid": "8",
    "ifiid": "10",
    "metro": "Dallas",
    "industry": "Health",
    "yrs_on_list": "1"
  },
  {
    "id": "21648",
    "rank": "4108",
    "workers": "2150",
    "company": "Great Lakes Caring Home Health and Hospice",
    "url": "great-lakes-caring-home-health-and-hospice",
    "state_l": "Michigan",
    "state_s": "MI",
    "city": "Jackson",
    "growth": "69.2083",
    "revenue": "188866292",
    "ifmid": "303",
    "ifiid": "10",
    "metro": "Jackson, MI",
    "industry": "Health",
    "yrs_on_list": "8"
  },
  {
    "id": "9156",
    "rank": "4154",
    "workers": "622",
    "company": "Ivie & Associates",
    "url": "ivie-associates",
    "state_l": "Texas",
    "state_s": "TX",
    "city": "Flower Mound",
    "growth": "67.0849",
    "revenue": "460519135",
    "ifmid": "8",
    "ifiid": "5",
    "metro": "Dallas",
    "industry": "Advertising & Marketing",
    "yrs_on_list": "4"
  },
  {
    "id": "26237",
    "rank": "4155",
    "workers": "2423",
    "company": "Academy Mortgage",
    "url": "academy-mortgage",
    "state_l": "Utah",
    "state_s": "UT",
    "city": "Draper",
    "growth": "67.0302",
    "revenue": "419635303",
    "ifmid": "12",
    "ifiid": "2",
    "metro": "Salt Lake City",
    "industry": "Financial Services",
    "yrs_on_list": "3"
  },
  {
    "id": "981",
    "rank": "4159",
    "workers": "802",
    "company": "Phacil",
    "url": "phacil",
    "state_l": "Virginia",
    "state_s": "VA",
    "city": "Arlington",
    "growth": "66.8667",
    "revenue": "126158974",
    "ifmid": "3",
    "ifiid": "8",
    "metro": "Washington, DC",
    "industry": "IT Services",
    "yrs_on_list": "10"
  },
  {
    "id": "2662",
    "rank": "4176",
    "workers": "1187",
    "company": "M S International",
    "url": "m-s-international",
    "state_l": "California",
    "state_s": "CA",
    "city": "Orange",
    "growth": "66.1547",
    "revenue": "759169000",
    "ifmid": "2",
    "ifiid": "4",
    "metro": "Los Angeles",
    "industry": "Consumer Products & Services",
    "yrs_on_list": "7"
  },
  {
    "id": "22630",
    "rank": "4177",
    "workers": "760",
    "company": "American Technologies",
    "url": "american-technologies",
    "state_l": "California",
    "state_s": "CA",
    "city": "Orange",
    "growth": "66.1286",
    "revenue": "180837756",
    "ifmid": "2",
    "ifiid": "20",
    "metro": "Los Angeles",
    "industry": "Construction",
    "yrs_on_list": "8"
  },
  {
    "id": "926",
    "rank": "4205",
    "workers": "3272",
    "company": "Vaco",
    "url": "vaco",
    "state_l": "Tennessee",
    "state_s": "TN",
    "city": "Brentwood",
    "growth": "64.9437",
    "revenue": "291353261",
    "ifmid": "82",
    "ifiid": "17",
    "metro": "Nashville",
    "industry": "Business Products & Services",
    "yrs_on_list": "10"
  },
  {
    "id": "44410",
    "rank": "4206",
    "workers": "750",
    "company": "Alterman",
    "url": "alterman",
    "state_l": "Texas",
    "state_s": "TX",
    "city": "San Antonio",
    "growth": "64.8705",
    "revenue": "147447000",
    "ifmid": "14",
    "ifiid": "20",
    "metro": "San Antonio, TX",
    "industry": "Construction",
    "yrs_on_list": "1"
  },
  {
    "id": "24353",
    "rank": "4212",
    "workers": "620",
    "company": "The Learning Experience",
    "url": "the-learning-experience",
    "state_l": "Florida",
    "state_s": "FL",
    "city": "Boca Raton",
    "growth": "64.7771",
    "revenue": "48142310",
    "ifmid": "1",
    "ifiid": "19",
    "metro": "Miami",
    "industry": "Education",
    "yrs_on_list": "4"
  },
  {
    "id": "18161",
    "rank": "4222",
    "workers": "1300",
    "company": "Orion Systems Integrators",
    "url": "orion-systems-integrators",
    "state_l": "New Jersey",
    "state_s": "NJ",
    "city": "Monmouth Junction",
    "growth": "64.4383",
    "revenue": "85549000",
    "ifmid": "9",
    "ifiid": "8",
    "metro": "New York City",
    "industry": "IT Services",
    "yrs_on_list": "7"
  },
  {
    "id": "7685",
    "rank": "4231",
    "workers": "650",
    "company": "Gateway Mortgage Group",
    "url": "gateway-mortgage-group",
    "state_l": "Oklahoma",
    "state_s": "OK",
    "city": "Tulsa",
    "growth": "64.2522",
    "revenue": "130254787",
    "ifmid": "841",
    "ifiid": "2",
    "metro": "Tulsa, OK",
    "industry": "Financial Services",
    "yrs_on_list": "6"
  },
  {
    "id": "26331",
    "rank": "4257",
    "workers": "1405",
    "company": "United Shore",
    "url": "united-shore",
    "state_l": "Michigan",
    "state_s": "MI",
    "city": "Troy",
    "growth": "63.4569",
    "revenue": "510126000",
    "ifmid": "50",
    "ifiid": "2",
    "metro": "Detroit",
    "industry": "Financial Services",
    "yrs_on_list": "3"
  },
  {
    "id": "22756",
    "rank": "4261",
    "workers": "12600",
    "company": "Key Safety Systems",
    "url": "key-safety-systems",
    "state_l": "Michigan",
    "state_s": "MI",
    "city": "Sterling Heights",
    "growth": "63.3667",
    "revenue": "1592767414",
    "ifmid": "50",
    "ifiid": "15",
    "metro": "Detroit",
    "industry": "Manufacturing",
    "yrs_on_list": "5"
  },
  {
    "id": "17245",
    "rank": "4279",
    "workers": "675",
    "company": "Lexicon Consulting",
    "url": "lexicon-consulting",
    "state_l": "California",
    "state_s": "CA",
    "city": "San Diego",
    "growth": "62.9978",
    "revenue": "16571957",
    "ifmid": "11",
    "ifiid": "7",
    "metro": "San Diego",
    "industry": "Government Services",
    "yrs_on_list": "2"
  },
  {
    "id": "44428",
    "rank": "4298",
    "workers": "950",
    "company": "Altamarea Group",
    "url": "altamarea-group",
    "state_l": "New York",
    "state_s": "NY",
    "city": "New York",
    "growth": "62.5253",
    "revenue": "65680336",
    "ifmid": "9",
    "ifiid": "11",
    "metro": "New York City",
    "industry": "Food & Beverage",
    "yrs_on_list": "1"
  },
  {
    "id": "171",
    "rank": "4323",
    "workers": "4000",
    "company": "GeBBS Healthcare Solutions",
    "url": "gebbs-healthcare-solutions",
    "state_l": "California",
    "state_s": "CA",
    "city": "Marina del Rey",
    "growth": "61.5505",
    "revenue": "30223078",
    "ifmid": "2",
    "ifiid": "10",
    "metro": "Los Angeles",
    "industry": "Health",
    "yrs_on_list": "8"
  },
  {
    "id": "1605",
    "rank": "4326",
    "workers": "3791",
    "company": "Total Quality Logistics",
    "url": "total-quality-logistics",
    "state_l": "Ohio",
    "state_s": "OH",
    "city": "Cincinnati",
    "growth": "61.4511",
    "revenue": "2239908520",
    "ifmid": "47",
    "ifiid": "6",
    "metro": "Cincinnati",
    "industry": "Logistics & Transportation",
    "yrs_on_list": "12"
  },
  {
    "id": "44433",
    "rank": "4334",
    "workers": "1449",
    "company": "The Flame Broiler",
    "url": "the-flame-broiler",
    "state_l": "California",
    "state_s": "CA",
    "city": "Santa Ana",
    "growth": "61.2009",
    "revenue": "98163871",
    "ifmid": "2",
    "ifiid": "11",
    "metro": "Los Angeles",
    "industry": "Food & Beverage",
    "yrs_on_list": "1"
  },
  {
    "id": "486",
    "rank": "4349",
    "workers": "763",
    "company": "Carenet Healthcare Services",
    "url": "carenet-healthcare-services",
    "state_l": "Texas",
    "state_s": "TX",
    "city": "San Antonio",
    "growth": "60.4458",
    "revenue": "47549151",
    "ifmid": "14",
    "ifiid": "10",
    "metro": "San Antonio, TX",
    "industry": "Health",
    "yrs_on_list": "8"
  },
  {
    "id": "44439",
    "rank": "4365",
    "workers": "3700",
    "company": "GMS INC.",
    "url": "gms-inc",
    "state_l": "Georgia",
    "state_s": "GA",
    "city": "Tucker",
    "growth": "59.9661",
    "revenue": "1858182000",
    "ifmid": "29",
    "ifiid": "20",
    "metro": "Atlanta",
    "industry": "Construction",
    "yrs_on_list": "1"
  },
  {
    "id": "6825",
    "rank": "4371",
    "workers": "2200",
    "company": "SEKO Logistics",
    "url": "seko-logistics",
    "state_l": "Illinois",
    "state_s": "IL",
    "city": "Itasca",
    "growth": "59.8731",
    "revenue": "527573000",
    "ifmid": "17",
    "ifiid": "6",
    "metro": "Chicago",
    "industry": "Logistics & Transportation",
    "yrs_on_list": "5"
  },
  {
    "id": "570",
    "rank": "4380",
    "workers": "700",
    "company": "Telogis",
    "url": "telogis",
    "state_l": "California",
    "state_s": "CA",
    "city": "Aliso Viejo",
    "growth": "59.7019",
    "revenue": "110944396",
    "ifmid": "2",
    "ifiid": "9",
    "metro": "Los Angeles",
    "industry": "Software",
    "yrs_on_list": "9"
  },
  {
    "id": "592",
    "rank": "4396",
    "workers": "4622",
    "company": "eClinicalWorks",
    "url": "eclinicalworks",
    "state_l": "Massachusetts",
    "state_s": "MA",
    "city": "Westborough",
    "growth": "59.2296",
    "revenue": "402000000",
    "ifmid": "1024",
    "ifiid": "10",
    "metro": "Worcester, MA-CT",
    "industry": "Health",
    "yrs_on_list": "10"
  },
  {
    "id": "2746",
    "rank": "4438",
    "workers": "1181",
    "company": "Paycor",
    "url": "paycor",
    "state_l": "Ohio",
    "state_s": "OH",
    "city": "Cincinnati",
    "growth": "58.0507",
    "revenue": "144293542",
    "ifmid": "47",
    "ifiid": "21",
    "metro": "Cincinnati",
    "industry": "Human Resources",
    "yrs_on_list": "8"
  },
  {
    "id": "775",
    "rank": "4452",
    "workers": "737",
    "company": "Viverae",
    "url": "viverae",
    "state_l": "Texas",
    "state_s": "TX",
    "city": "Dallas",
    "growth": "57.5791",
    "revenue": "37154429",
    "ifmid": "8",
    "ifiid": "10",
    "metro": "Dallas",
    "industry": "Health",
    "yrs_on_list": "6"
  },
  {
    "id": "38118",
    "rank": "4453",
    "workers": "700",
    "company": "Revature",
    "url": "revature",
    "state_l": "Virginia",
    "state_s": "VA",
    "city": "Reston",
    "growth": "57.5716",
    "revenue": "56526655",
    "ifmid": "3",
    "ifiid": "19",
    "metro": "Washington, DC",
    "industry": "Education",
    "yrs_on_list": "2"
  },
  {
    "id": "38270",
    "rank": "4471",
    "workers": "1139",
    "company": "Port Logistics Group",
    "url": "port-logistics-group",
    "state_l": "California",
    "state_s": "CA",
    "city": "City of Industry",
    "growth": "57.1454",
    "revenue": "191750391",
    "ifmid": "2",
    "ifiid": "6",
    "metro": "Los Angeles",
    "industry": "Logistics & Transportation",
    "yrs_on_list": "2"
  },
  {
    "id": "44463",
    "rank": "4484",
    "workers": "617",
    "company": "TSP",
    "url": "tsp",
    "state_l": "Texas",
    "state_s": "TX",
    "city": "Dallas",
    "growth": "56.5697",
    "revenue": "63644000",
    "ifmid": "8",
    "ifiid": "8",
    "metro": "Dallas",
    "industry": "IT Services",
    "yrs_on_list": "1"
  },
  {
    "id": "23573",
    "rank": "4497",
    "workers": "870",
    "company": "SCIO Health Analytics",
    "url": "scio-health-analytics",
    "state_l": "Connecticut",
    "state_s": "CT",
    "city": "West Hartford",
    "growth": "56.1832",
    "revenue": "58943237",
    "ifmid": "100",
    "ifiid": "10",
    "metro": "Hartford-West Hartford-East Hartford, CT",
    "industry": "Health",
    "yrs_on_list": "5"
  },
  {
    "id": "44468",
    "rank": "4503",
    "workers": "4030",
    "company": "American Renal Associates",
    "url": "american-renal-associates",
    "state_l": "Massachusetts",
    "state_s": "MA",
    "city": "Beverly",
    "growth": "56.0039",
    "revenue": "657505000",
    "ifmid": "6",
    "ifiid": "10",
    "metro": "Boston",
    "industry": "Health",
    "yrs_on_list": "1"
  },
  {
    "id": "21199",
    "rank": "4505",
    "workers": "1777",
    "company": "New Penn Financial",
    "url": "new-penn-financial",
    "state_l": "Pennsylvania",
    "state_s": "PA",
    "city": "Plymouth Meeting",
    "growth": "55.978",
    "revenue": "275408082",
    "ifmid": "49",
    "ifiid": "2",
    "metro": "Philadelphia",
    "industry": "Financial Services",
    "yrs_on_list": "5"
  },
  {
    "id": "24750",
    "rank": "4509",
    "workers": "3717",
    "company": "Summit Security Services",
    "url": "summit-security-services",
    "state_l": "New York",
    "state_s": "NY",
    "city": "Uniondale",
    "growth": "55.8446",
    "revenue": "146984154",
    "ifmid": "9",
    "ifiid": "13",
    "metro": "New York City",
    "industry": "Security",
    "yrs_on_list": "3"
  },
  {
    "id": "38096",
    "rank": "4512",
    "workers": "1111",
    "company": "TASC",
    "url": "tasc",
    "state_l": "Wisconsin",
    "state_s": "WI",
    "city": "Madison",
    "growth": "55.8045",
    "revenue": "98708807",
    "ifmid": "78",
    "ifiid": "21",
    "metro": "Madison, WI",
    "industry": "Human Resources",
    "yrs_on_list": "2"
  },
  {
    "id": "20681",
    "rank": "4557",
    "workers": "2939",
    "company": "Sterling Talent Solutions",
    "url": "sterling-talent-solutions",
    "state_l": "New York",
    "state_s": "NY",
    "city": "New York",
    "growth": "54.4423",
    "revenue": "331980808",
    "ifmid": "9",
    "ifiid": "21",
    "metro": "New York City",
    "industry": "Human Resources",
    "yrs_on_list": "7"
  },
  {
    "id": "2053",
    "rank": "4561",
    "workers": "4752",
    "company": "Cellular Sales of Knoxville",
    "url": "cellular-sales-of-knoxville",
    "state_l": "Tennessee",
    "state_s": "TN",
    "city": "Knoxville",
    "growth": "54.2943",
    "revenue": "1437095068",
    "ifmid": "99",
    "ifiid": "18",
    "metro": "Knoxville, TN",
    "industry": "Retail",
    "yrs_on_list": "8"
  },
  {
    "id": "20780",
    "rank": "4572",
    "workers": "810",
    "company": "Whitlock",
    "url": "whitlock",
    "state_l": "Virginia",
    "state_s": "VA",
    "city": "Richmond",
    "growth": "53.8236",
    "revenue": "271498130",
    "ifmid": "40",
    "ifiid": "17",
    "metro": "Richmond, VA",
    "industry": "Business Products & Services",
    "yrs_on_list": "7"
  },
  {
    "id": "4392",
    "rank": "4588",
    "workers": "800",
    "company": "Market America",
    "url": "market-america",
    "state_l": "North Carolina",
    "state_s": "NC",
    "city": "GREENSBORO",
    "growth": "53.4595",
    "revenue": "791081690",
    "ifmid": "287",
    "ifiid": "18",
    "metro": "Greensboro-High Point, NC",
    "industry": "Retail",
    "yrs_on_list": "4"
  },
  {
    "id": "4149",
    "rank": "4589",
    "workers": "1978",
    "company": "Pro Mach",
    "url": "pro-mach",
    "state_l": "Kentucky",
    "state_s": "KY",
    "city": "Covington",
    "growth": "53.4547",
    "revenue": "533080000",
    "ifmid": "47",
    "ifiid": "15",
    "metro": "Cincinnati",
    "industry": "Manufacturing",
    "yrs_on_list": "6"
  },
  {
    "id": "4789",
    "rank": "4611",
    "workers": "1276",
    "company": "American Specialty Health",
    "url": "american-specialty-health",
    "state_l": "Indiana",
    "state_s": "IN",
    "city": "Carmel",
    "growth": "52.6585",
    "revenue": "331902950",
    "ifmid": "81",
    "ifiid": "10",
    "metro": "Indianapolis, IN",
    "industry": "Health",
    "yrs_on_list": "7"
  },
  {
    "id": "24518",
    "rank": "4613",
    "workers": "698",
    "company": "Sikich",
    "url": "sikich",
    "state_l": "Illinois",
    "state_s": "IL",
    "city": "Naperville",
    "growth": "52.5836",
    "revenue": "116607127",
    "ifmid": "17",
    "ifiid": "17",
    "metro": "Chicago",
    "industry": "Business Products & Services",
    "yrs_on_list": "4"
  },
  {
    "id": "3650",
    "rank": "4627",
    "workers": "1586",
    "company": "Resource Options",
    "url": "resource-options",
    "state_l": "Massachusetts",
    "state_s": "MA",
    "city": "Needham",
    "growth": "52.228",
    "revenue": "22267524",
    "ifmid": "6",
    "ifiid": "21",
    "metro": "Boston",
    "industry": "Human Resources",
    "yrs_on_list": "7"
  },
  {
    "id": "6846",
    "rank": "4655",
    "workers": "725",
    "company": "ProTrans",
    "url": "protrans",
    "state_l": "Indiana",
    "state_s": "IN",
    "city": "Indianapolis",
    "growth": "51.2954",
    "revenue": "291561259",
    "ifmid": "81",
    "ifiid": "6",
    "metro": "Indianapolis, IN",
    "industry": "Logistics & Transportation",
    "yrs_on_list": "6"
  },
  {
    "id": "19036",
    "rank": "4701",
    "workers": "1880",
    "company": "Morgan Lewis",
    "url": "morgan-lewis",
    "state_l": "New York",
    "state_s": "NY",
    "city": "New York",
    "growth": "49.9187",
    "revenue": "1844000000",
    "ifmid": "9",
    "ifiid": "17",
    "metro": "New York City",
    "industry": "Business Products & Services",
    "yrs_on_list": "3"
  },
  {
    "id": "22705",
    "rank": "4703",
    "workers": "1010",
    "company": "PW Companies",
    "url": "pw-companies",
    "state_l": "Utah",
    "state_s": "UT",
    "city": "Sandy",
    "growth": "49.8608",
    "revenue": "61846827",
    "ifmid": "12",
    "ifiid": "18",
    "metro": "Salt Lake City",
    "industry": "Retail",
    "yrs_on_list": "3"
  },
  {
    "id": "2364",
    "rank": "4725",
    "workers": "1165",
    "company": "IST Management Services",
    "url": "ist-management-services",
    "state_l": "Georgia",
    "state_s": "GA",
    "city": "Atlanta",
    "growth": "49.2614",
    "revenue": "61871331",
    "ifmid": "29",
    "ifiid": "17",
    "metro": "Atlanta",
    "industry": "Business Products & Services",
    "yrs_on_list": "7"
  },
  {
    "id": "22088",
    "rank": "4739",
    "workers": "720",
    "company": "Polsinelli",
    "url": "polsinelli",
    "state_l": "Missouri",
    "state_s": "MO",
    "city": "Kansas City",
    "growth": "48.8203",
    "revenue": "410000000",
    "ifmid": "21",
    "ifiid": "17",
    "metro": "Kansas City, MO-KS",
    "industry": "Business Products & Services",
    "yrs_on_list": "5"
  },
  {
    "id": "38105",
    "rank": "4755",
    "workers": "1190",
    "company": "AIM Consulting Group",
    "url": "aim-consulting-group",
    "state_l": "Washington",
    "state_s": "WA",
    "city": "Bellevue",
    "growth": "48.2771",
    "revenue": "97798607",
    "ifmid": "23",
    "ifiid": "8",
    "metro": "Seattle",
    "industry": "IT Services",
    "yrs_on_list": "2"
  },
  {
    "id": "17227",
    "rank": "4756",
    "workers": "1396",
    "company": "Granite Telecommunications",
    "url": "granite-telecommunications",
    "state_l": "Massachusetts",
    "state_s": "MA",
    "city": "Quincy",
    "growth": "48.264",
    "revenue": "1091579000",
    "ifmid": "6",
    "ifiid": "14",
    "metro": "Boston",
    "industry": "Telecommunications",
    "yrs_on_list": "10"
  },
  {
    "id": "9162",
    "rank": "4766",
    "workers": "14887",
    "company": "Exact Staff",
    "url": "exact-staff",
    "state_l": "California",
    "state_s": "CA",
    "city": "Woodland Hills",
    "growth": "47.9807",
    "revenue": "65002000",
    "ifmid": "2",
    "ifiid": "21",
    "metro": "Los Angeles",
    "industry": "Human Resources",
    "yrs_on_list": "4"
  },
  {
    "id": "18679",
    "rank": "4772",
    "workers": "801",
    "company": "Cooley",
    "url": "cooley",
    "state_l": "New York",
    "state_s": "NY",
    "city": "New York",
    "growth": "47.812",
    "revenue": "912000000",
    "ifmid": "998",
    "ifiid": "17",
    "metro": null,
    "industry": "Business Products & Services",
    "yrs_on_list": "3"
  },
  {
    "id": "1154",
    "rank": "4774",
    "workers": "1457",
    "company": "InGenesis",
    "url": "ingenesis",
    "state_l": "Texas",
    "state_s": "TX",
    "city": "San Antonio",
    "growth": "47.7541",
    "revenue": "123122770",
    "ifmid": "14",
    "ifiid": "17",
    "metro": "San Antonio, TX",
    "industry": "Business Products & Services",
    "yrs_on_list": "9"
  },
  {
    "id": "1778",
    "rank": "4787",
    "workers": "3612",
    "company": "TransPerfect",
    "url": "transperfect",
    "state_l": "New York",
    "state_s": "NY",
    "city": "New York",
    "growth": "47.378",
    "revenue": "504599185",
    "ifmid": "9",
    "ifiid": "17",
    "metro": "New York City",
    "industry": "Business Products & Services",
    "yrs_on_list": "9"
  },
  {
    "id": "20823",
    "rank": "4790",
    "workers": "656",
    "company": "Workplace options",
    "url": "workplace-options",
    "state_l": "North Carolina",
    "state_s": "NC",
    "city": "Raleigh",
    "growth": "47.3067",
    "revenue": "56517998",
    "ifmid": "1029",
    "ifiid": "21",
    "metro": "Raleigh, NC",
    "industry": "Human Resources",
    "yrs_on_list": "6"
  },
  {
    "id": "18885",
    "rank": "4796",
    "workers": "1106",
    "company": "Ropes & Gray",
    "url": "ropes-gray",
    "state_l": "Massachusetts",
    "state_s": "MA",
    "city": "Boston",
    "growth": "47.0899",
    "revenue": "1390000000",
    "ifmid": "6",
    "ifiid": "17",
    "metro": "Boston",
    "industry": "Business Products & Services",
    "yrs_on_list": "4"
  },
  {
    "id": "6987",
    "rank": "4803",
    "workers": "3100",
    "company": "Technosoft",
    "url": "technosoft",
    "state_l": "Michigan",
    "state_s": "MI",
    "city": "Southfield",
    "growth": "46.8985",
    "revenue": "123216267",
    "ifmid": "50",
    "ifiid": "8",
    "metro": "Detroit",
    "industry": "IT Services",
    "yrs_on_list": "3"
  },
  {
    "id": "44537",
    "rank": "4813",
    "workers": "640",
    "company": "Milk Specialties Global",
    "url": "milk-specialties-global",
    "state_l": "Minnesota",
    "state_s": "MN",
    "city": "Eden Prairie",
    "growth": "46.5473",
    "revenue": "736186000",
    "ifmid": "13",
    "ifiid": "15",
    "metro": "Minneapolis",
    "industry": "Manufacturing",
    "yrs_on_list": "1"
  },
  {
    "id": "8128",
    "rank": "4872",
    "workers": "3632",
    "company": "AmWINS Group",
    "url": "amwins-group",
    "state_l": "North Carolina",
    "state_s": "NC",
    "city": "Charlotte",
    "growth": "44.7639",
    "revenue": "774522800",
    "ifmid": "43",
    "ifiid": "1",
    "metro": "Charlotte",
    "industry": "Insurance",
    "yrs_on_list": "7"
  },
  {
    "id": "3568",
    "rank": "4879",
    "workers": "600",
    "company": "Anisa International",
    "url": "anisa-international",
    "state_l": "Georgia",
    "state_s": "GA",
    "city": "atlanta",
    "growth": "44.5869",
    "revenue": "45932962",
    "ifmid": "29",
    "ifiid": "15",
    "metro": "Atlanta",
    "industry": "Manufacturing",
    "yrs_on_list": "5"
  },
  {
    "id": "1779",
    "rank": "4917",
    "workers": "1136",
    "company": "Talentburst",
    "url": "talentburst",
    "state_l": "Massachusetts",
    "state_s": "MA",
    "city": "Natick",
    "growth": "43.2448",
    "revenue": "57533997",
    "ifmid": "6",
    "ifiid": "8",
    "metro": "Boston",
    "industry": "IT Services",
    "yrs_on_list": "10"
  },
  {
    "id": "3813",
    "rank": "4937",
    "workers": "7036",
    "company": "Pacific Dental Services",
    "url": "pacific-dental-services",
    "state_l": "California",
    "state_s": "CA",
    "city": "Irvine",
    "growth": "42.4371",
    "revenue": "893898000",
    "ifmid": "2",
    "ifiid": "10",
    "metro": "Los Angeles",
    "industry": "Health",
    "yrs_on_list": "11"
  },
  {
    "id": "21328",
    "rank": "4969",
    "workers": "625",
    "company": "Advanced Enterprises of NW FL",
    "url": "advanced-enterprises-of-nw-fl",
    "state_l": "Florida",
    "state_s": "FL",
    "city": "Mary Esther",
    "growth": "41.1365",
    "revenue": "87922375",
    "ifmid": "130",
    "ifiid": "5",
    "metro": "Pensacola-Ferry Pass-Brent, FL",
    "industry": "Advertising & Marketing",
    "yrs_on_list": "5"
  },
  {
    "id": "20473",
    "rank": "4990",
    "workers": "2323",
    "company": "Accurate Home Care",
    "url": "accurate-home-care",
    "state_l": "Minnesota",
    "state_s": "MN",
    "city": "Otsego",
    "growth": "40.2554",
    "revenue": "58817000",
    "ifmid": "13",
    "ifiid": "10",
    "metro": "Minneapolis",
    "industry": "Health",
    "yrs_on_list": "6"
  },
  {
    "id": "23258",
    "rank": "4998",
    "workers": "1951",
    "company": "Stratosphere Quality",
    "url": "stratosphere-quality",
    "state_l": "Indiana",
    "state_s": "IN",
    "city": "Fishers",
    "growth": "39.7451",
    "revenue": "102252325",
    "ifmid": "81",
    "ifiid": "15",
    "metro": "Indianapolis, IN",
    "industry": "Manufacturing",
    "yrs_on_list": "4"
  }
]